Workbook

Sheet P&L
A1: Deal model P&L
A3: EUR m | F3: 2024A | G3: 2025A | H3: 2026E | I3: 2027E | J3: 2028E
A4: Revenue | F4: 176.5 | G4: 188 | H4: =G4*(1+Assumptions!$C$4) | I4: =H4*(1+Assumptions!$C$4) | J4: =I4*(1+Assumptions!$C$4)
A5: COGS | F5: =-F4*Assumptions!$C$5 | G5: =G4*Assumptions!$C$5 | H5: =-H4*Assumptions!$C$5 | I5: =-I4*Assumptions!$C$5 | J5: =-J4*Assumptions!$C$6
A6: Gross profit | F6: =F4+F5 | G6: =G4+G5 | H6: =H4+H5 | I6: 95.6544 | J6: =J4+J5
A7: Direct costs | F7: =-F4*Assumptions!$C$6 | G7: =-G4*Assumptions!$C$6 | H7: =-H4*Assumptions!$C$6 | I7: =-I4*Assumptions!$C$6 | J7: =-J4*Assumptions!$C$6
A8: Overhead | F8: =-F4*Assumptions!$C$7 | G8: =-G4*Assumptions!$C$7 | H8: =-H4*Assumptions!$C$7 | I8: =-I4*Assumptions!$C$7 | J8: =-J4*Assumptions!$C$7
A9: Operating expenses | F9: =SUM(F7:F8) | G9: =SUM(G7:G8) | H9: =SUM(H7:H8) | I9: =SUM(I7:I8) | J9: =SUM(J7:J8)
A10: EBITDA | F10: =F6+F9 | G10: =G6+G9 | H10: =H6+H9 | I10: =I6+I9 | J10: =J6+J9
A11: EBITDA margin | F11: =F10/F4 | G11: =G10/G4 | H11: =H10/H4 | I11: =I10/I4 | J11: =J10/J4

Sheet Assumptions
B4: Revenue growth | C4: 0.06
B5: COGS % of revenue | C5: 0.52
B6: Direct cost % of revenue | C6: 0.18
B7: Overhead % of revenue | C7: 0.14

Sheet Summary
A1: Deal summary
A3: EUR m | F3: 2024A | G3: 2025A | H3: 2026E | I3: 2027E | J3: 2028E
A5: EBITDA | F5: ='P&L'!F10 | G5: ='P&L'!G10 | H5: ='P&L'!H10 | I5: ='P&L'!I10 | J5: ='P&L'!J10
A6: YoY EBITDA change | G6: =G5/F5-1 | H6: =H5/G5-1 | I6: =I5/H5-1 | J6: =J5/I5-1
