Workbook
Name COD: Inputs!$E$10
Name Demand: Inputs!$E$5
Name DiscRate: Inputs!$E$8
Name GridEsc: Inputs!$E$7
Name GridPrice: Inputs!$E$6
Name Hours: Inputs!$E$11
Name Scenario: Inputs!$E$12
Name ScenMult: Inputs!$E$13
Name Tenor: Inputs!$E$9

Sheet Cover
C1: European Corporate PPA Evaluation Model
C2: Renewable PPA offers across Europe for XY Company
B4: 1 | C4: Workbook map
C5: Assumptions | D5: Offtaker profile, financial settings, price scenario and the PPA offer register (all inputs).
C6: Calc | D6: Annual engine: timeline, generation, capture prices, CfD settlement, offtaker costs.
C7: Results | D7: Offer ranking, NPV, breakeven strike, hedge coverage and comparison charts.
C8: Project View | D8: Drill-down into one selected offer with its annual profile and charts.
B10: =+B4+1 -> 2 | C10: Units
C11: MWh | D11: Energy
C12: EUR/MWh | D12: Electricity prices
C13: EUR k | D13: Cash Flows
B15: =B10+1 -> 3 | C15: Cell colour convention
C16: 1,250 | D16: Hardcoded input - edit these cells only
C17: 1,250 | D17: Link to another sheet
C18: 1,250 | D18: Formula on the same sheet
B20: =+B15+1 -> 4 | C20: Model integrity
C21: All checks | D21: =IF(Calc!G139=0,"OK - all checks pass","ERROR - see Calc checks") -> OK - all checks pass

Sheet Inputs
C1: Inputs
C2: Main inputs of the model
B4: 1 | C4: Offtaker & financial settings
C5: Offtaker annual electricity demand | D5: MWh | E5: 240000
C6: Retail grid power price (year 1) | D6: EUR/MWh | E6: 105
C7: Grid power price escalator | D7: % | E7: -0.01
C8: Discount rate | D8: % | E8: 0.075
C9: PPA tenor | D9: years | E9: 15
C10: Commercial operation date | D10: date | E10: 46388
C11: Hours per year | D11: hours | E11: 8760
C12: Wholesale price scenario | D12: text | E12: Base
C13: Capture price multiplier (active) | D13: ratio | E13: =INDEX($E$16:$E$18,MATCH(Scenario,$C$16:$C$18,0)) -> 1
B15: =+B4+1 -> 2 | C15: Wholesale price scenarios
C16: Low | D16: ratio | E16: 0.85
C17: Base | D17: ratio | E17: 1
C18: High | D18: ratio | E18: 1.15
B20: =+B15+1 -> 3 | C20: PPA offer register
C22: Offer ID | D22: Country | E22: Technology | F22: Capacity (MW) | G22: Capacity factor (%) | H22: Degradation (%) | I22: Peak gen. share (%) | J22: Off-peak gen. share (%) | K22: Peak capture price (EUR/MWh) | L22: Off-peak capture price (EUR/MWh) | M22: Wholesale escalator (%) | N22: PPA strike price (EUR/MWh) | O22: PPA indexation (%) | P22: Year-1 generation (MWh) | Q22: Year-1 demand coverage (%)
C23: ES-PV1 | D23: Spain | E23: Solar PV | F23: 95 | G23: 0.21 | H23: 0.005 | I23: 0.7 | J23: =1-I23 -> 0.3 | K23: 62 | L23: 38 | M23: -0.01 | N23: 38 | O23: 0.01 | P23: =F23*G23*Hours -> 174762 | Q23: =IF(Demand=0,0,P23/Demand) -> 0.728175
C24: PT-PV1 | D24: Portugal | E24: Solar PV | F24: 70 | G24: 0.2 | H24: 0.005 | I24: 0.7 | J24: =1-I24 -> 0.3 | K24: 60 | L24: 40 | M24: -0.01 | N24: 40 | O24: 0.01 | P24: =F24*G24*Hours -> 122640 | Q24: =IF(Demand=0,0,P24/Demand) -> 0.511
C25: IT-PV1 | D25: Italy (Sud) | E25: Solar PV | F25: 80 | G25: 0.18 | H25: 0.005 | I25: 0.7 | J25: =1-I25 -> 0.3 | K25: 115 | L25: 95 | M25: -0.03 | N25: 78 | O25: 0 | P25: =F25*G25*Hours -> 126144 | Q25: =IF(Demand=0,0,P25/Demand) -> 0.5256
C26: GR-PV1 | D26: Greece | E26: Solar PV | F26: 75 | G26: 0.2 | H26: 0.005 | I26: 0.7 | J26: =1-I26 -> 0.3 | K26: 98 | L26: 80 | M26: -0.02 | N26: 58 | O26: 0.005 | P26: =F26*G26*Hours -> 131400 | Q26: =IF(Demand=0,0,P26/Demand) -> 0.5475
C27: FR-WN1 | D27: France | E27: Onshore wind | F27: 60 | G27: 0.25 | H27: 0 | I27: 0.5 | J27: =1-I27 -> 0.5 | K27: 68 | L27: 58 | M27: 0.01 | N27: 64 | O27: 0.01 | P27: =F27*G27*Hours -> 131400 | Q27: =IF(Demand=0,0,P27/Demand) -> 0.5475
C28: DE-WN1 | D28: Germany | E28: Onshore wind | F28: 65 | G28: 0.24 | H28: 0 | I28: 0.5 | J28: =1-I28 -> 0.5 | K28: 92 | L28: 70 | M28: -0.005 | N28: 72 | O28: 0.01 | P28: =F28*G28*Hours -> 136656 | Q28: =IF(Demand=0,0,P28/Demand) -> 0.5694
C29: NL-OW1 | D29: Netherlands | E29: Offshore wind | F29: 45 | G29: 0.42 | H29: 0 | I29: 0.5 | J29: =1-I29 -> 0.5 | K29: 88 | L29: 72 | M29: 0 | N29: 80 | O29: 0.015 | P29: =F29*G29*Hours -> 165564 | Q29: =IF(Demand=0,0,P29/Demand) -> 0.68985
C30: PL-WN1 | D30: Poland | E30: Onshore wind | F30: 55 | G30: 0.3 | H30: 0 | I30: 0.5 | J30: =1-I30 -> 0.5 | K30: 110 | L30: 95 | M30: -0.015 | N30: 82 | O30: 0.01 | P30: =F30*G30*Hours -> 144540 | Q30: =IF(Demand=0,0,P30/Demand) -> 0.60225
C31: SE-WN1 | D31: Sweden (SE3) | E31: Onshore wind | F31: 60 | G31: 0.33 | H31: 0 | I31: 0.5 | J31: =1-I31 -> 0.5 | K31: 55 | L31: 35 | M31: 0.005 | N31: 36 | O31: 0.01 | P31: =F31*G31*Hours -> 173448 | Q31: =IF(Demand=0,0,P31/Demand) -> 0.7227
C32: FI-WN1 | D32: Finland | E32: Onshore wind | F32: 50 | G32: 0.35 | H32: 0 | I32: 0.5 | J32: =1-I32 -> 0.5 | K32: 58 | L32: 32 | M32: -0.01 | N32: 38 | O32: 0.01 | P32: =F32*G32*Hours -> 153300 | Q32: =IF(Demand=0,0,P32/Demand) -> 0.63875

Sheet Calc
C1: Calculations
C2: Year-by-year calculations
G3: Total / avg
C4: Contract year | F4: # | I4: 1 | J4: =I4+1 -> 2 | K4: =J4+1 -> 3 | L4: =K4+1 -> 4 | M4: =L4+1 -> 5 | N4: =M4+1 -> 6 | O4: =N4+1 -> 7 | P4: =O4+1 -> 8 | Q4: =P4+1 -> 9 | ... W4: =V4+1 -> 15
C5: Calendar year | F5: year | I5: =YEAR(COD)+I$4-1 -> 2027 | J5: =YEAR(COD)+J$4-1 -> 2028 | K5: =YEAR(COD)+K$4-1 -> 2029 | L5: =YEAR(COD)+L$4-1 -> 2030 | M5: =YEAR(COD)+M$4-1 -> 2031 | N5: =YEAR(COD)+N$4-1 -> 2032 | O5: =YEAR(COD)+O$4-1 -> 2033 | P5: =YEAR(COD)+P$4-1 -> 2034 | ... W5: =YEAR(COD)+W$4-1 -> 2041
C6: Operating flag | F6: flag | G6: =SUM(I6:W6) -> 15 | I6: =IF(I$4<=Tenor,1,0) -> 1 | J6: =IF(J$4<=Tenor,1,0) -> 1 | K6: =IF(K$4<=Tenor,1,0) -> 1 | L6: =IF(L$4<=Tenor,1,0) -> 1 | M6: =IF(M$4<=Tenor,1,0) -> 1 | N6: =IF(N$4<=Tenor,1,0) -> 1 | O6: =IF(O$4<=Tenor,1,0) -> 1 | P6: =IF(P$4<=Tenor,1,0) -> 1 | ... W6: =IF(W$4<=Tenor,1,0) -> 1
C7: Discount factor | F7: ratio | I7: =1/(1+DiscRate)^((DATE(I$5,12,31)-(COD-1))/365) -> 0.93023256 | J7: =1/(1+DiscRate)^((DATE(J$5,12,31)-(COD-1))/365) -> 0.86516117 | K7: =1/(1+DiscRate)^((DATE(K$5,12,31)-(COD-1))/365) -> 0.80480109 | L7: =1/(1+DiscRate)^((DATE(L$5,12,31)-(COD-1))/365) -> 0.74865218 | M7: =1/(1+DiscRate)^((DATE(M$5,12,31)-(COD-1))/365) -> 0.69642063 | N7: =1/(1+DiscRate)^((DATE(N$5,12,31)-(COD-1))/365) -> 0.6477048 | O7: =1/(1+DiscRate)^((DATE(O$5,12,31)-(COD-1))/365) -> 0.60251609 | P7: =1/(1+DiscRate)^((DATE(P$5,12,31)-(COD-1))/365) -> 0.56048008 | ... W7: =1/(1+DiscRate)^((DATE(W$5,12,31)-(COD-1))/365) -> 0.33769827
B9: 1 | C9: Offtaker baseline
C10: Electricity demand | F10: MWh | G10: =SUM(I10:W10) -> 3600000 | I10: =Demand*I$6 -> 240000 | J10: =Demand*J$6 -> 240000 | K10: =Demand*K$6 -> 240000 | L10: =Demand*L$6 -> 240000 | M10: =Demand*M$6 -> 240000 | N10: =Demand*N$6 -> 240000 | O10: =Demand*O$6 -> 240000 | P10: =Demand*P$6 -> 240000 | ... W10: =Demand*W$6 -> 240000
C11: Retail grid power price | F11: EUR/MWh | G11: =IF(G10=0,0,G12*1000/G10) -> 97.959152 | I11: =GridPrice*(1+GridEsc)^(I$4-1)*I$6 -> 105 | J11: =GridPrice*(1+GridEsc)^(J$4-1)*J$6 -> 103.95 | K11: =GridPrice*(1+GridEsc)^(K$4-1)*K$6 -> 102.9105 | L11: =GridPrice*(1+GridEsc)^(L$4-1)*L$6 -> 101.88139 | M11: =GridPrice*(1+GridEsc)^(M$4-1)*M$6 -> 100.86258 | N11: =GridPrice*(1+GridEsc)^(N$4-1)*N$6 -> 99.853955 | O11: =GridPrice*(1+GridEsc)^(O$4-1)*O$6 -> 98.855416 | P11: =GridPrice*(1+GridEsc)^(P$4-1)*P$6 -> 97.866862 | ... W11: =GridPrice*(1+GridEsc)^(W$4-1)*W$6 -> 91.21831
C12: Unhedged electricity cost | F12: EUR k | G12: =SUM(I12:W12) -> 352652.95 | I12: =I10*I11/1000 -> 25200 | J12: =J10*J11/1000 -> 24948 | K12: =K10*K11/1000 -> 24698.52 | L12: =L10*L11/1000 -> 24451.535 | M12: =M10*M11/1000 -> 24207.019 | N12: =N10*N11/1000 -> 23964.949 | O12: =O10*O11/1000 -> 23725.3 | P12: =P10*P11/1000 -> 23488.047 | ... W12: =W10*W11/1000 -> 21892.394
B14: =+B9+1 -> 2 | C14: Generation
C15: =Inputs!$C$23 -> ES-PV1 | D15: =Inputs!$D$23 -> Spain | E15: =Inputs!$E$23 -> Solar PV | F15: MWh | G15: =SUM(I15:W15) -> 2531638.4 | I15: =Inputs!$F$23*Inputs!$G$23*Hours*(1-Inputs!$H$23)^(I$4-1)*I$6 -> 174762 | J15: =Inputs!$F$23*Inputs!$G$23*Hours*(1-Inputs!$H$23)^(J$4-1)*J$6 -> 173888.19 | K15: =Inputs!$F$23*Inputs!$G$23*Hours*(1-Inputs!$H$23)^(K$4-1)*K$6 -> 173018.75 | L15: =Inputs!$F$23*Inputs!$G$23*Hours*(1-Inputs!$H$23)^(L$4-1)*L$6 -> 172153.66 | M15: =Inputs!$F$23*Inputs!$G$23*Hours*(1-Inputs!$H$23)^(M$4-1)*M$6 -> 171292.89 | N15: =Inputs!$F$23*Inputs!$G$23*Hours*(1-Inputs!$H$23)^(N$4-1)*N$6 -> 170436.42 | O15: =Inputs!$F$23*Inputs!$G$23*Hours*(1-Inputs!$H$23)^(O$4-1)*O$6 -> 169584.24 | P15: =Inputs!$F$23*Inputs!$G$23*Hours*(1-Inputs!$H$23)^(P$4-1)*P$6 -> 168736.32 | ... W15: =Inputs!$F$23*Inputs!$G$23*Hours*(1-Inputs!$H$23)^(W$4-1)*W$6 -> 162918.4
C16: =Inputs!$C$24 -> PT-PV1 | D16: =Inputs!$D$24 -> Portugal | E16: =Inputs!$E$24 -> Solar PV | F16: MWh | G16: =SUM(I16:W16) -> 1776588.3 | I16: =Inputs!$F$24*Inputs!$G$24*Hours*(1-Inputs!$H$24)^(I$4-1)*I$6 -> 122640 | J16: =Inputs!$F$24*Inputs!$G$24*Hours*(1-Inputs!$H$24)^(J$4-1)*J$6 -> 122026.8 | K16: =Inputs!$F$24*Inputs!$G$24*Hours*(1-Inputs!$H$24)^(K$4-1)*K$6 -> 121416.67 | L16: =Inputs!$F$24*Inputs!$G$24*Hours*(1-Inputs!$H$24)^(L$4-1)*L$6 -> 120809.58 | M16: =Inputs!$F$24*Inputs!$G$24*Hours*(1-Inputs!$H$24)^(M$4-1)*M$6 -> 120205.53 | N16: =Inputs!$F$24*Inputs!$G$24*Hours*(1-Inputs!$H$24)^(N$4-1)*N$6 -> 119604.51 | O16: =Inputs!$F$24*Inputs!$G$24*Hours*(1-Inputs!$H$24)^(O$4-1)*O$6 -> 119006.48 | P16: =Inputs!$F$24*Inputs!$G$24*Hours*(1-Inputs!$H$24)^(P$4-1)*P$6 -> 118411.45 | ... W16: =Inputs!$F$24*Inputs!$G$24*Hours*(1-Inputs!$H$24)^(W$4-1)*W$6 -> 114328.7
C17: =Inputs!$C$25 -> IT-PV1 | D17: =Inputs!$D$25 -> Italy (Sud) | E17: =Inputs!$E$25 -> Solar PV | F17: MWh | G17: =SUM(I17:W17) -> 1827348 | I17: =Inputs!$F$25*Inputs!$G$25*Hours*(1-Inputs!$H$25)^(I$4-1)*I$6 -> 126144 | J17: =Inputs!$F$25*Inputs!$G$25*Hours*(1-Inputs!$H$25)^(J$4-1)*J$6 -> 125513.28 | K17: =Inputs!$F$25*Inputs!$G$25*Hours*(1-Inputs!$H$25)^(K$4-1)*K$6 -> 124885.71 | L17: =Inputs!$F$25*Inputs!$G$25*Hours*(1-Inputs!$H$25)^(L$4-1)*L$6 -> 124261.29 | M17: =Inputs!$F$25*Inputs!$G$25*Hours*(1-Inputs!$H$25)^(M$4-1)*M$6 -> 123639.98 | N17: =Inputs!$F$25*Inputs!$G$25*Hours*(1-Inputs!$H$25)^(N$4-1)*N$6 -> 123021.78 | O17: =Inputs!$F$25*Inputs!$G$25*Hours*(1-Inputs!$H$25)^(O$4-1)*O$6 -> 122406.67 | P17: =Inputs!$F$25*Inputs!$G$25*Hours*(1-Inputs!$H$25)^(P$4-1)*P$6 -> 121794.64 | ... W17: =Inputs!$F$25*Inputs!$G$25*Hours*(1-Inputs!$H$25)^(W$4-1)*W$6 -> 117595.24
C18: =Inputs!$C$26 -> GR-PV1 | D18: =Inputs!$D$26 -> Greece | E18: =Inputs!$E$26 -> Solar PV | F18: MWh | G18: =SUM(I18:W18) -> 1903487.5 | I18: =Inputs!$F$26*Inputs!$G$26*Hours*(1-Inputs!$H$26)^(I$4-1)*I$6 -> 131400 | J18: =Inputs!$F$26*Inputs!$G$26*Hours*(1-Inputs!$H$26)^(J$4-1)*J$6 -> 130743 | K18: =Inputs!$F$26*Inputs!$G$26*Hours*(1-Inputs!$H$26)^(K$4-1)*K$6 -> 130089.29 | L18: =Inputs!$F$26*Inputs!$G$26*Hours*(1-Inputs!$H$26)^(L$4-1)*L$6 -> 129438.84 | M18: =Inputs!$F$26*Inputs!$G$26*Hours*(1-Inputs!$H$26)^(M$4-1)*M$6 -> 128791.64 | N18: =Inputs!$F$26*Inputs!$G$26*Hours*(1-Inputs!$H$26)^(N$4-1)*N$6 -> 128147.69 | O18: =Inputs!$F$26*Inputs!$G$26*Hours*(1-Inputs!$H$26)^(O$4-1)*O$6 -> 127506.95 | P18: =Inputs!$F$26*Inputs!$G$26*Hours*(1-Inputs!$H$26)^(P$4-1)*P$6 -> 126869.41 | ... W18: =Inputs!$F$26*Inputs!$G$26*Hours*(1-Inputs!$H$26)^(W$4-1)*W$6 -> 122495.04
C19: =Inputs!$C$27 -> FR-WN1 | D19: =Inputs!$D$27 -> France | E19: =Inputs!$E$27 -> Onshore wind | F19: MWh | G19: =SUM(I19:W19) -> 1971000 | I19: =Inputs!$F$27*Inputs!$G$27*Hours*(1-Inputs!$H$27)^(I$4-1)*I$6 -> 131400 | J19: =Inputs!$F$27*Inputs!$G$27*Hours*(1-Inputs!$H$27)^(J$4-1)*J$6 -> 131400 | K19: =Inputs!$F$27*Inputs!$G$27*Hours*(1-Inputs!$H$27)^(K$4-1)*K$6 -> 131400 | L19: =Inputs!$F$27*Inputs!$G$27*Hours*(1-Inputs!$H$27)^(L$4-1)*L$6 -> 131400 | M19: =Inputs!$F$27*Inputs!$G$27*Hours*(1-Inputs!$H$27)^(M$4-1)*M$6 -> 131400 | N19: =Inputs!$F$27*Inputs!$G$27*Hours*(1-Inputs!$H$27)^(N$4-1)*N$6 -> 131400 | O19: =Inputs!$F$27*Inputs!$G$27*Hours*(1-Inputs!$H$27)^(O$4-1)*O$6 -> 131400 | P19: =Inputs!$F$27*Inputs!$G$27*Hours*(1-Inputs!$H$27)^(P$4-1)*P$6 -> 131400 | ... W19: =Inputs!$F$27*Inputs!$G$27*Hours*(1-Inputs!$H$27)^(W$4-1)*W$6 -> 131400
C20: =Inputs!$C$28 -> DE-WN1 | D20: =Inputs!$D$28 -> Germany | E20: =Inputs!$E$28 -> Onshore wind | F20: MWh | G20: =SUM(I20:W20) -> 2049840 | I20: =Inputs!$F$28*Inputs!$G$28*Hours*(1-Inputs!$H$28)^(I$4-1)*I$6 -> 136656 | J20: =Inputs!$F$28*Inputs!$G$28*Hours*(1-Inputs!$H$28)^(J$4-1)*J$6 -> 136656 | K20: =Inputs!$F$28*Inputs!$G$28*Hours*(1-Inputs!$H$28)^(K$4-1)*K$6 -> 136656 | L20: =Inputs!$F$28*Inputs!$G$28*Hours*(1-Inputs!$H$28)^(L$4-1)*L$6 -> 136656 | M20: =Inputs!$F$28*Inputs!$G$28*Hours*(1-Inputs!$H$28)^(M$4-1)*M$6 -> 136656 | N20: =Inputs!$F$28*Inputs!$G$28*Hours*(1-Inputs!$H$28)^(N$4-1)*N$6 -> 136656 | O20: =Inputs!$F$28*Inputs!$G$28*Hours*(1-Inputs!$H$28)^(O$4-1)*O$6 -> 136656 | P20: =Inputs!$F$28*Inputs!$G$28*Hours*(1-Inputs!$H$28)^(P$4-1)*P$6 -> 136656 | ... W20: =Inputs!$F$28*Inputs!$G$28*Hours*(1-Inputs!$H$28)^(W$4-1)*W$6 -> 136656
C21: =Inputs!$C$29 -> NL-OW1 | D21: =Inputs!$D$29 -> Netherlands | E21: =Inputs!$E$29 -> Offshore wind | F21: MWh | G21: =SUM(I21:W21) -> 2483460 | I21: =Inputs!$F$29*Inputs!$G$29*Hours*(1-Inputs!$H$29)^(I$4-1)*I$6 -> 165564 | J21: =Inputs!$F$29*Inputs!$G$29*Hours*(1-Inputs!$H$29)^(J$4-1)*J$6 -> 165564 | K21: =Inputs!$F$29*Inputs!$G$29*Hours*(1-Inputs!$H$29)^(K$4-1)*K$6 -> 165564 | L21: =Inputs!$F$29*Inputs!$G$29*Hours*(1-Inputs!$H$29)^(L$4-1)*L$6 -> 165564 | M21: =Inputs!$F$29*Inputs!$G$29*Hours*(1-Inputs!$H$29)^(M$4-1)*M$6 -> 165564 | N21: =Inputs!$F$29*Inputs!$G$29*Hours*(1-Inputs!$H$29)^(N$4-1)*N$6 -> 165564 | O21: =Inputs!$F$29*Inputs!$G$29*Hours*(1-Inputs!$H$29)^(O$4-1)*O$6 -> 165564 | P21: =Inputs!$F$29*Inputs!$G$29*Hours*(1-Inputs!$H$29)^(P$4-1)*P$6 -> 165564 | ... W21: =Inputs!$F$29*Inputs!$G$29*Hours*(1-Inputs!$H$29)^(W$4-1)*W$6 -> 165564
C22: =Inputs!$C$30 -> PL-WN1 | D22: =Inputs!$D$30 -> Poland | E22: =Inputs!$E$30 -> Onshore wind | F22: MWh | G22: =SUM(I22:W22) -> 2168100 | I22: =Inputs!$F$30*Inputs!$G$30*Hours*(1-Inputs!$H$30)^(I$4-1)*I$6 -> 144540 | J22: =Inputs!$F$30*Inputs!$G$30*Hours*(1-Inputs!$H$30)^(J$4-1)*J$6 -> 144540 | K22: =Inputs!$F$30*Inputs!$G$30*Hours*(1-Inputs!$H$30)^(K$4-1)*K$6 -> 144540 | L22: =Inputs!$F$30*Inputs!$G$30*Hours*(1-Inputs!$H$30)^(L$4-1)*L$6 -> 144540 | M22: =Inputs!$F$30*Inputs!$G$30*Hours*(1-Inputs!$H$30)^(M$4-1)*M$6 -> 144540 | N22: =Inputs!$F$30*Inputs!$G$30*Hours*(1-Inputs!$H$30)^(N$4-1)*N$6 -> 144540 | O22: =Inputs!$F$30*Inputs!$G$30*Hours*(1-Inputs!$H$30)^(O$4-1)*O$6 -> 144540 | P22: =Inputs!$F$30*Inputs!$G$30*Hours*(1-Inputs!$H$30)^(P$4-1)*P$6 -> 144540 | ... W22: =Inputs!$F$30*Inputs!$G$30*Hours*(1-Inputs!$H$30)^(W$4-1)*W$6 -> 144540
C23: =Inputs!$C$31 -> SE-WN1 | D23: =Inputs!$D$31 -> Sweden (SE3) | E23: =Inputs!$E$31 -> Onshore wind | F23: MWh | G23: =SUM(I23:W23) -> 2601720 | I23: =Inputs!$F$31*Inputs!$G$31*Hours*(1-Inputs!$H$31)^(I$4-1)*I$6 -> 173448 | J23: =Inputs!$F$31*Inputs!$G$31*Hours*(1-Inputs!$H$31)^(J$4-1)*J$6 -> 173448 | K23: =Inputs!$F$31*Inputs!$G$31*Hours*(1-Inputs!$H$31)^(K$4-1)*K$6 -> 173448 | L23: =Inputs!$F$31*Inputs!$G$31*Hours*(1-Inputs!$H$31)^(L$4-1)*L$6 -> 173448 | M23: =Inputs!$F$31*Inputs!$G$31*Hours*(1-Inputs!$H$31)^(M$4-1)*M$6 -> 173448 | N23: =Inputs!$F$31*Inputs!$G$31*Hours*(1-Inputs!$H$31)^(N$4-1)*N$6 -> 173448 | O23: =Inputs!$F$31*Inputs!$G$31*Hours*(1-Inputs!$H$31)^(O$4-1)*O$6 -> 173448 | P23: =Inputs!$F$31*Inputs!$G$31*Hours*(1-Inputs!$H$31)^(P$4-1)*P$6 -> 173448 | ... W23: =Inputs!$F$31*Inputs!$G$31*Hours*(1-Inputs!$H$31)^(W$4-1)*W$6 -> 173448
C24: =Inputs!$C$32 -> FI-WN1 | D24: =Inputs!$D$32 -> Finland | E24: =Inputs!$E$32 -> Onshore wind | F24: MWh | G24: =SUM(I24:W24) -> 2299500 | I24: =Inputs!$F$32*Inputs!$G$32*Hours*(1-Inputs!$H$32)^(I$4-1)*I$6 -> 153300 | J24: =Inputs!$F$32*Inputs!$G$32*Hours*(1-Inputs!$H$32)^(J$4-1)*J$6 -> 153300 | K24: =Inputs!$F$32*Inputs!$G$32*Hours*(1-Inputs!$H$32)^(K$4-1)*K$6 -> 153300 | L24: =Inputs!$F$32*Inputs!$G$32*Hours*(1-Inputs!$H$32)^(L$4-1)*L$6 -> 153300 | M24: =Inputs!$F$32*Inputs!$G$32*Hours*(1-Inputs!$H$32)^(M$4-1)*M$6 -> 153300 | N24: =Inputs!$F$32*Inputs!$G$32*Hours*(1-Inputs!$H$32)^(N$4-1)*N$6 -> 153300 | O24: =Inputs!$F$32*Inputs!$G$32*Hours*(1-Inputs!$H$32)^(O$4-1)*O$6 -> 153300 | P24: =Inputs!$F$32*Inputs!$G$32*Hours*(1-Inputs!$H$32)^(P$4-1)*P$6 -> 153300 | ... W24: =Inputs!$F$32*Inputs!$G$32*Hours*(1-Inputs!$H$32)^(W$4-1)*W$6 -> 153300
B26: =+B14+1 -> 3 | C26: Demand coverage
C27: =Inputs!$C$23 -> ES-PV1 | D27: =Inputs!$D$23 -> Spain | E27: =Inputs!$E$23 -> Solar PV | F27: % | G27: =IF($G$10=0,0,G15/$G$10) -> 0.70323288 | I27: =IF(I$10=0,0,I15/I$10) -> 0.728175 | J27: =IF(J$10=0,0,J15/J$10) -> 0.72453413 | K27: =IF(K$10=0,0,K15/K$10) -> 0.72091145 | L27: =IF(L$10=0,0,L15/L$10) -> 0.7173069 | M27: =IF(M$10=0,0,M15/M$10) -> 0.71372036 | N27: =IF(N$10=0,0,N15/N$10) -> 0.71015176 | O27: =IF(O$10=0,0,O15/O$10) -> 0.706601 | P27: =IF(P$10=0,0,P15/P$10) -> 0.703068 | ... W27: =IF(W$10=0,0,W15/W$10) -> 0.67882667
C28: =Inputs!$C$24 -> PT-PV1 | D28: =Inputs!$D$24 -> Portugal | E28: =Inputs!$E$24 -> Solar PV | F28: % | G28: =IF($G$10=0,0,G16/$G$10) -> 0.49349676 | I28: =IF(I$10=0,0,I16/I$10) -> 0.511 | J28: =IF(J$10=0,0,J16/J$10) -> 0.508445 | K28: =IF(K$10=0,0,K16/K$10) -> 0.50590278 | L28: =IF(L$10=0,0,L16/L$10) -> 0.50337326 | M28: =IF(M$10=0,0,M16/M$10) -> 0.50085639 | N28: =IF(N$10=0,0,N16/N$10) -> 0.49835211 | O28: =IF(O$10=0,0,O16/O$10) -> 0.49586035 | P28: =IF(P$10=0,0,P16/P$10) -> 0.49338105 | ... W28: =IF(W$10=0,0,W16/W$10) -> 0.47636959
C29: =Inputs!$C$25 -> IT-PV1 | D29: =Inputs!$D$25 -> Italy (Sud) | E29: =Inputs!$E$25 -> Solar PV | F29: % | G29: =IF($G$10=0,0,G17/$G$10) -> 0.50759667 | I29: =IF(I$10=0,0,I17/I$10) -> 0.5256 | J29: =IF(J$10=0,0,J17/J$10) -> 0.522972 | K29: =IF(K$10=0,0,K17/K$10) -> 0.52035714 | L29: =IF(L$10=0,0,L17/L$10) -> 0.51775535 | M29: =IF(M$10=0,0,M17/M$10) -> 0.51516658 | N29: =IF(N$10=0,0,N17/N$10) -> 0.51259074 | O29: =IF(O$10=0,0,O17/O$10) -> 0.51002779 | P29: =IF(P$10=0,0,P17/P$10) -> 0.50747765 | ... W29: =IF(W$10=0,0,W17/W$10) -> 0.48998015
C30: =Inputs!$C$26 -> GR-PV1 | D30: =Inputs!$D$26 -> Greece | E30: =Inputs!$E$26 -> Solar PV | F30: % | G30: =IF($G$10=0,0,G18/$G$10) -> 0.52874653 | I30: =IF(I$10=0,0,I18/I$10) -> 0.5475 | J30: =IF(J$10=0,0,J18/J$10) -> 0.5447625 | K30: =IF(K$10=0,0,K18/K$10) -> 0.54203869 | L30: =IF(L$10=0,0,L18/L$10) -> 0.53932849 | M30: =IF(M$10=0,0,M18/M$10) -> 0.53663185 | N30: =IF(N$10=0,0,N18/N$10) -> 0.53394869 | O30: =IF(O$10=0,0,O18/O$10) -> 0.53127895 | P30: =IF(P$10=0,0,P18/P$10) -> 0.52862255 | ... W30: =IF(W$10=0,0,W18/W$10) -> 0.51039599
C31: =Inputs!$C$27 -> FR-WN1 | D31: =Inputs!$D$27 -> France | E31: =Inputs!$E$27 -> Onshore wind | F31: % | G31: =IF($G$10=0,0,G19/$G$10) -> 0.5475 | I31: =IF(I$10=0,0,I19/I$10) -> 0.5475 | J31: =IF(J$10=0,0,J19/J$10) -> 0.5475 | K31: =IF(K$10=0,0,K19/K$10) -> 0.5475 | L31: =IF(L$10=0,0,L19/L$10) -> 0.5475 | M31: =IF(M$10=0,0,M19/M$10) -> 0.5475 | N31: =IF(N$10=0,0,N19/N$10) -> 0.5475 | O31: =IF(O$10=0,0,O19/O$10) -> 0.5475 | P31: =IF(P$10=0,0,P19/P$10) -> 0.5475 | ... W31: =IF(W$10=0,0,W19/W$10) -> 0.5475
C32: =Inputs!$C$28 -> DE-WN1 | D32: =Inputs!$D$28 -> Germany | E32: =Inputs!$E$28 -> Onshore wind | F32: % | G32: =IF($G$10=0,0,G20/$G$10) -> 0.5694 | I32: =IF(I$10=0,0,I20/I$10) -> 0.5694 | J32: =IF(J$10=0,0,J20/J$10) -> 0.5694 | K32: =IF(K$10=0,0,K20/K$10) -> 0.5694 | L32: =IF(L$10=0,0,L20/L$10) -> 0.5694 | M32: =IF(M$10=0,0,M20/M$10) -> 0.5694 | N32: =IF(N$10=0,0,N20/N$10) -> 0.5694 | O32: =IF(O$10=0,0,O20/O$10) -> 0.5694 | P32: =IF(P$10=0,0,P20/P$10) -> 0.5694 | ... W32: =IF(W$10=0,0,W20/W$10) -> 0.5694
C33: =Inputs!$C$29 -> NL-OW1 | D33: =Inputs!$D$29 -> Netherlands | E33: =Inputs!$E$29 -> Offshore wind | F33: % | G33: =IF($G$10=0,0,G21/$G$10) -> 0.68985 | I33: =IF(I$10=0,0,I21/I$10) -> 0.68985 | J33: =IF(J$10=0,0,J21/J$10) -> 0.68985 | K33: =IF(K$10=0,0,K21/K$10) -> 0.68985 | L33: =IF(L$10=0,0,L21/L$10) -> 0.68985 | M33: =IF(M$10=0,0,M21/M$10) -> 0.68985 | N33: =IF(N$10=0,0,N21/N$10) -> 0.68985 | O33: =IF(O$10=0,0,O21/O$10) -> 0.68985 | P33: =IF(P$10=0,0,P21/P$10) -> 0.68985 | ... W33: =IF(W$10=0,0,W21/W$10) -> 0.68985
C34: =Inputs!$C$30 -> PL-WN1 | D34: =Inputs!$D$30 -> Poland | E34: =Inputs!$E$30 -> Onshore wind | F34: % | G34: =IF($G$10=0,0,G22/$G$10) -> 0.60225 | I34: =IF(I$10=0,0,I22/I$10) -> 0.60225 | J34: =IF(J$10=0,0,J22/J$10) -> 0.60225 | K34: =IF(K$10=0,0,K22/K$10) -> 0.60225 | L34: =IF(L$10=0,0,L22/L$10) -> 0.60225 | M34: =IF(M$10=0,0,M22/M$10) -> 0.60225 | N34: =IF(N$10=0,0,N22/N$10) -> 0.60225 | O34: =IF(O$10=0,0,O22/O$10) -> 0.60225 | P34: =IF(P$10=0,0,P22/P$10) -> 0.60225 | ... W34: =IF(W$10=0,0,W22/W$10) -> 0.60225
C35: =Inputs!$C$31 -> SE-WN1 | D35: =Inputs!$D$31 -> Sweden (SE3) | E35: =Inputs!$E$31 -> Onshore wind | F35: % | G35: =IF($G$10=0,0,G23/$G$10) -> 0.7227 | I35: =IF(I$10=0,0,I23/I$10) -> 0.7227 | J35: =IF(J$10=0,0,J23/J$10) -> 0.7227 | K35: =IF(K$10=0,0,K23/K$10) -> 0.7227 | L35: =IF(L$10=0,0,L23/L$10) -> 0.7227 | M35: =IF(M$10=0,0,M23/M$10) -> 0.7227 | N35: =IF(N$10=0,0,N23/N$10) -> 0.7227 | O35: =IF(O$10=0,0,O23/O$10) -> 0.7227 | P35: =IF(P$10=0,0,P23/P$10) -> 0.7227 | ... W35: =IF(W$10=0,0,W23/W$10) -> 0.7227
C36: =Inputs!$C$32 -> FI-WN1 | D36: =Inputs!$D$32 -> Finland | E36: =Inputs!$E$32 -> Onshore wind | F36: % | G36: =IF($G$10=0,0,G24/$G$10) -> 0.63875 | I36: =IF(I$10=0,0,I24/I$10) -> 0.63875 | J36: =IF(J$10=0,0,J24/J$10) -> 0.63875 | K36: =IF(K$10=0,0,K24/K$10) -> 0.63875 | L36: =IF(L$10=0,0,L24/L$10) -> 0.63875 | M36: =IF(M$10=0,0,M24/M$10) -> 0.63875 | N36: =IF(N$10=0,0,N24/N$10) -> 0.63875 | O36: =IF(O$10=0,0,O24/O$10) -> 0.63875 | P36: =IF(P$10=0,0,P24/P$10) -> 0.63875 | ... W36: =IF(W$10=0,0,W24/W$10) -> 0.63875
B38: =+B26+1 -> 4 | C38: Capture price
C39: =Inputs!$C$23 -> ES-PV1 | D39: =Inputs!$D$23 -> Spain | E39: =Inputs!$E$23 -> Solar PV | F39: EUR/MWh | G39: =IF(G15=0,0,G75*1000/G15) -> 51.173411 | I39: =(Inputs!$I$23*Inputs!$K$23+Inputs!$J$23*Inputs!$L$23)*ScenMult*(1+Inputs!$M$23)^(I$4-1)*I$6 -> 54.8 | J39: =(Inputs!$I$23*Inputs!$K$23+Inputs!$J$23*Inputs!$L$23)*ScenMult*(1+Inputs!$M$23)^(J$4-1)*J$6 -> 54.252 | K39: =(Inputs!$I$23*Inputs!$K$23+Inputs!$J$23*Inputs!$L$23)*ScenMult*(1+Inputs!$M$23)^(K$4-1)*K$6 -> 53.70948 | L39: =(Inputs!$I$23*Inputs!$K$23+Inputs!$J$23*Inputs!$L$23)*ScenMult*(1+Inputs!$M$23)^(L$4-1)*L$6 -> 53.172385 | M39: =(Inputs!$I$23*Inputs!$K$23+Inputs!$J$23*Inputs!$L$23)*ScenMult*(1+Inputs!$M$23)^(M$4-1)*M$6 -> 52.640661 | N39: =(Inputs!$I$23*Inputs!$K$23+Inputs!$J$23*Inputs!$L$23)*ScenMult*(1+Inputs!$M$23)^(N$4-1)*N$6 -> 52.114255 | O39: =(Inputs!$I$23*Inputs!$K$23+Inputs!$J$23*Inputs!$L$23)*ScenMult*(1+Inputs!$M$23)^(O$4-1)*O$6 -> 51.593112 | P39: =(Inputs!$I$23*Inputs!$K$23+Inputs!$J$23*Inputs!$L$23)*ScenMult*(1+Inputs!$M$23)^(P$4-1)*P$6 -> 51.077181 | ... W39: =(Inputs!$I$23*Inputs!$K$23+Inputs!$J$23*Inputs!$L$23)*ScenMult*(1+Inputs!$M$23)^(W$4-1)*W$6 -> 47.607271
C40: =Inputs!$C$24 -> PT-PV1 | D40: =Inputs!$D$24 -> Portugal | E40: =Inputs!$E$24 -> Solar PV | F40: EUR/MWh | G40: =IF(G16=0,0,G76*1000/G16) -> 50.426354 | I40: =(Inputs!$I$24*Inputs!$K$24+Inputs!$J$24*Inputs!$L$24)*ScenMult*(1+Inputs!$M$24)^(I$4-1)*I$6 -> 54 | J40: =(Inputs!$I$24*Inputs!$K$24+Inputs!$J$24*Inputs!$L$24)*ScenMult*(1+Inputs!$M$24)^(J$4-1)*J$6 -> 53.46 | K40: =(Inputs!$I$24*Inputs!$K$24+Inputs!$J$24*Inputs!$L$24)*ScenMult*(1+Inputs!$M$24)^(K$4-1)*K$6 -> 52.9254 | L40: =(Inputs!$I$24*Inputs!$K$24+Inputs!$J$24*Inputs!$L$24)*ScenMult*(1+Inputs!$M$24)^(L$4-1)*L$6 -> 52.396146 | M40: =(Inputs!$I$24*Inputs!$K$24+Inputs!$J$24*Inputs!$L$24)*ScenMult*(1+Inputs!$M$24)^(M$4-1)*M$6 -> 51.872185 | N40: =(Inputs!$I$24*Inputs!$K$24+Inputs!$J$24*Inputs!$L$24)*ScenMult*(1+Inputs!$M$24)^(N$4-1)*N$6 -> 51.353463 | O40: =(Inputs!$I$24*Inputs!$K$24+Inputs!$J$24*Inputs!$L$24)*ScenMult*(1+Inputs!$M$24)^(O$4-1)*O$6 -> 50.839928 | P40: =(Inputs!$I$24*Inputs!$K$24+Inputs!$J$24*Inputs!$L$24)*ScenMult*(1+Inputs!$M$24)^(P$4-1)*P$6 -> 50.331529 | ... W40: =(Inputs!$I$24*Inputs!$K$24+Inputs!$J$24*Inputs!$L$24)*ScenMult*(1+Inputs!$M$24)^(W$4-1)*W$6 -> 46.912274
C41: =Inputs!$C$25 -> IT-PV1 | D41: =Inputs!$D$25 -> Italy (Sud) | E41: =Inputs!$E$25 -> Solar PV | F41: EUR/MWh | G41: =IF(G17=0,0,G77*1000/G17) -> 89.087127 | I41: =(Inputs!$I$25*Inputs!$K$25+Inputs!$J$25*Inputs!$L$25)*ScenMult*(1+Inputs!$M$25)^(I$4-1)*I$6 -> 109 | J41: =(Inputs!$I$25*Inputs!$K$25+Inputs!$J$25*Inputs!$L$25)*ScenMult*(1+Inputs!$M$25)^(J$4-1)*J$6 -> 105.73 | K41: =(Inputs!$I$25*Inputs!$K$25+Inputs!$J$25*Inputs!$L$25)*ScenMult*(1+Inputs!$M$25)^(K$4-1)*K$6 -> 102.5581 | L41: =(Inputs!$I$25*Inputs!$K$25+Inputs!$J$25*Inputs!$L$25)*ScenMult*(1+Inputs!$M$25)^(L$4-1)*L$6 -> 99.481357 | M41: =(Inputs!$I$25*Inputs!$K$25+Inputs!$J$25*Inputs!$L$25)*ScenMult*(1+Inputs!$M$25)^(M$4-1)*M$6 -> 96.496916 | N41: =(Inputs!$I$25*Inputs!$K$25+Inputs!$J$25*Inputs!$L$25)*ScenMult*(1+Inputs!$M$25)^(N$4-1)*N$6 -> 93.602009 | O41: =(Inputs!$I$25*Inputs!$K$25+Inputs!$J$25*Inputs!$L$25)*ScenMult*(1+Inputs!$M$25)^(O$4-1)*O$6 -> 90.793949 | P41: =(Inputs!$I$25*Inputs!$K$25+Inputs!$J$25*Inputs!$L$25)*ScenMult*(1+Inputs!$M$25)^(P$4-1)*P$6 -> 88.07013 | ... W41: =(Inputs!$I$25*Inputs!$K$25+Inputs!$J$25*Inputs!$L$25)*ScenMult*(1+Inputs!$M$25)^(W$4-1)*W$6 -> 71.159154
C42: =Inputs!$C$26 -> GR-PV1 | D42: =Inputs!$D$26 -> Greece | E42: =Inputs!$E$26 -> Solar PV | F42: EUR/MWh | G42: =IF(G18=0,0,G78*1000/G18) -> 80.847351 | I42: =(Inputs!$I$26*Inputs!$K$26+Inputs!$J$26*Inputs!$L$26)*ScenMult*(1+Inputs!$M$26)^(I$4-1)*I$6 -> 92.6 | J42: =(Inputs!$I$26*Inputs!$K$26+Inputs!$J$26*Inputs!$L$26)*ScenMult*(1+Inputs!$M$26)^(J$4-1)*J$6 -> 90.748 | K42: =(Inputs!$I$26*Inputs!$K$26+Inputs!$J$26*Inputs!$L$26)*ScenMult*(1+Inputs!$M$26)^(K$4-1)*K$6 -> 88.93304 | L42: =(Inputs!$I$26*Inputs!$K$26+Inputs!$J$26*Inputs!$L$26)*ScenMult*(1+Inputs!$M$26)^(L$4-1)*L$6 -> 87.154379 | M42: =(Inputs!$I$26*Inputs!$K$26+Inputs!$J$26*Inputs!$L$26)*ScenMult*(1+Inputs!$M$26)^(M$4-1)*M$6 -> 85.411292 | N42: =(Inputs!$I$26*Inputs!$K$26+Inputs!$J$26*Inputs!$L$26)*ScenMult*(1+Inputs!$M$26)^(N$4-1)*N$6 -> 83.703066 | O42: =(Inputs!$I$26*Inputs!$K$26+Inputs!$J$26*Inputs!$L$26)*ScenMult*(1+Inputs!$M$26)^(O$4-1)*O$6 -> 82.029004 | P42: =(Inputs!$I$26*Inputs!$K$26+Inputs!$J$26*Inputs!$L$26)*ScenMult*(1+Inputs!$M$26)^(P$4-1)*P$6 -> 80.388424 | ... W42: =(Inputs!$I$26*Inputs!$K$26+Inputs!$J$26*Inputs!$L$26)*ScenMult*(1+Inputs!$M$26)^(W$4-1)*W$6 -> 69.787244
C43: =Inputs!$C$27 -> FR-WN1 | D43: =Inputs!$D$27 -> France | E43: =Inputs!$E$27 -> Onshore wind | F43: EUR/MWh | G43: =IF(G19=0,0,G79*1000/G19) -> 67.606961 | I43: =(Inputs!$I$27*Inputs!$K$27+Inputs!$J$27*Inputs!$L$27)*ScenMult*(1+Inputs!$M$27)^(I$4-1)*I$6 -> 63 | J43: =(Inputs!$I$27*Inputs!$K$27+Inputs!$J$27*Inputs!$L$27)*ScenMult*(1+Inputs!$M$27)^(J$4-1)*J$6 -> 63.63 | K43: =(Inputs!$I$27*Inputs!$K$27+Inputs!$J$27*Inputs!$L$27)*ScenMult*(1+Inputs!$M$27)^(K$4-1)*K$6 -> 64.2663 | L43: =(Inputs!$I$27*Inputs!$K$27+Inputs!$J$27*Inputs!$L$27)*ScenMult*(1+Inputs!$M$27)^(L$4-1)*L$6 -> 64.908963 | M43: =(Inputs!$I$27*Inputs!$K$27+Inputs!$J$27*Inputs!$L$27)*ScenMult*(1+Inputs!$M$27)^(M$4-1)*M$6 -> 65.558053 | N43: =(Inputs!$I$27*Inputs!$K$27+Inputs!$J$27*Inputs!$L$27)*ScenMult*(1+Inputs!$M$27)^(N$4-1)*N$6 -> 66.213633 | O43: =(Inputs!$I$27*Inputs!$K$27+Inputs!$J$27*Inputs!$L$27)*ScenMult*(1+Inputs!$M$27)^(O$4-1)*O$6 -> 66.875769 | P43: =(Inputs!$I$27*Inputs!$K$27+Inputs!$J$27*Inputs!$L$27)*ScenMult*(1+Inputs!$M$27)^(P$4-1)*P$6 -> 67.544527 | ... W43: =(Inputs!$I$27*Inputs!$K$27+Inputs!$J$27*Inputs!$L$27)*ScenMult*(1+Inputs!$M$27)^(W$4-1)*W$6 -> 72.416875
C44: =Inputs!$C$28 -> DE-WN1 | D44: =Inputs!$D$28 -> Germany | E44: =Inputs!$E$28 -> Onshore wind | F44: EUR/MWh | G44: =IF(G20=0,0,G80*1000/G20) -> 78.225514 | I44: =(Inputs!$I$28*Inputs!$K$28+Inputs!$J$28*Inputs!$L$28)*ScenMult*(1+Inputs!$M$28)^(I$4-1)*I$6 -> 81 | J44: =(Inputs!$I$28*Inputs!$K$28+Inputs!$J$28*Inputs!$L$28)*ScenMult*(1+Inputs!$M$28)^(J$4-1)*J$6 -> 80.595 | K44: =(Inputs!$I$28*Inputs!$K$28+Inputs!$J$28*Inputs!$L$28)*ScenMult*(1+Inputs!$M$28)^(K$4-1)*K$6 -> 80.192025 | L44: =(Inputs!$I$28*Inputs!$K$28+Inputs!$J$28*Inputs!$L$28)*ScenMult*(1+Inputs!$M$28)^(L$4-1)*L$6 -> 79.791065 | M44: =(Inputs!$I$28*Inputs!$K$28+Inputs!$J$28*Inputs!$L$28)*ScenMult*(1+Inputs!$M$28)^(M$4-1)*M$6 -> 79.39211 | N44: =(Inputs!$I$28*Inputs!$K$28+Inputs!$J$28*Inputs!$L$28)*ScenMult*(1+Inputs!$M$28)^(N$4-1)*N$6 -> 78.995149 | O44: =(Inputs!$I$28*Inputs!$K$28+Inputs!$J$28*Inputs!$L$28)*ScenMult*(1+Inputs!$M$28)^(O$4-1)*O$6 -> 78.600173 | P44: =(Inputs!$I$28*Inputs!$K$28+Inputs!$J$28*Inputs!$L$28)*ScenMult*(1+Inputs!$M$28)^(P$4-1)*P$6 -> 78.207172 | ... W44: =(Inputs!$I$28*Inputs!$K$28+Inputs!$J$28*Inputs!$L$28)*ScenMult*(1+Inputs!$M$28)^(W$4-1)*W$6 -> 75.51064
C45: =Inputs!$C$29 -> NL-OW1 | D45: =Inputs!$D$29 -> Netherlands | E45: =Inputs!$E$29 -> Offshore wind | F45: EUR/MWh | G45: =IF(G21=0,0,G81*1000/G21) -> 80 | I45: =(Inputs!$I$29*Inputs!$K$29+Inputs!$J$29*Inputs!$L$29)*ScenMult*(1+Inputs!$M$29)^(I$4-1)*I$6 -> 80 | J45: =(Inputs!$I$29*Inputs!$K$29+Inputs!$J$29*Inputs!$L$29)*ScenMult*(1+Inputs!$M$29)^(J$4-1)*J$6 -> 80 | K45: =(Inputs!$I$29*Inputs!$K$29+Inputs!$J$29*Inputs!$L$29)*ScenMult*(1+Inputs!$M$29)^(K$4-1)*K$6 -> 80 | L45: =(Inputs!$I$29*Inputs!$K$29+Inputs!$J$29*Inputs!$L$29)*ScenMult*(1+Inputs!$M$29)^(L$4-1)*L$6 -> 80 | M45: =(Inputs!$I$29*Inputs!$K$29+Inputs!$J$29*Inputs!$L$29)*ScenMult*(1+Inputs!$M$29)^(M$4-1)*M$6 -> 80 | N45: =(Inputs!$I$29*Inputs!$K$29+Inputs!$J$29*Inputs!$L$29)*ScenMult*(1+Inputs!$M$29)^(N$4-1)*N$6 -> 80 | O45: =(Inputs!$I$29*Inputs!$K$29+Inputs!$J$29*Inputs!$L$29)*ScenMult*(1+Inputs!$M$29)^(O$4-1)*O$6 -> 80 | P45: =(Inputs!$I$29*Inputs!$K$29+Inputs!$J$29*Inputs!$L$29)*ScenMult*(1+Inputs!$M$29)^(P$4-1)*P$6 -> 80 | ... W45: =(Inputs!$I$29*Inputs!$K$29+Inputs!$J$29*Inputs!$L$29)*ScenMult*(1+Inputs!$M$29)^(W$4-1)*W$6 -> 80
C46: =Inputs!$C$30 -> PL-WN1 | D46: =Inputs!$D$30 -> Poland | E46: =Inputs!$E$30 -> Onshore wind | F46: EUR/MWh | G46: =IF(G22=0,0,G82*1000/G22) -> 92.406596 | I46: =(Inputs!$I$30*Inputs!$K$30+Inputs!$J$30*Inputs!$L$30)*ScenMult*(1+Inputs!$M$30)^(I$4-1)*I$6 -> 102.5 | J46: =(Inputs!$I$30*Inputs!$K$30+Inputs!$J$30*Inputs!$L$30)*ScenMult*(1+Inputs!$M$30)^(J$4-1)*J$6 -> 100.9625 | K46: =(Inputs!$I$30*Inputs!$K$30+Inputs!$J$30*Inputs!$L$30)*ScenMult*(1+Inputs!$M$30)^(K$4-1)*K$6 -> 99.448063 | L46: =(Inputs!$I$30*Inputs!$K$30+Inputs!$J$30*Inputs!$L$30)*ScenMult*(1+Inputs!$M$30)^(L$4-1)*L$6 -> 97.956342 | M46: =(Inputs!$I$30*Inputs!$K$30+Inputs!$J$30*Inputs!$L$30)*ScenMult*(1+Inputs!$M$30)^(M$4-1)*M$6 -> 96.486996 | N46: =(Inputs!$I$30*Inputs!$K$30+Inputs!$J$30*Inputs!$L$30)*ScenMult*(1+Inputs!$M$30)^(N$4-1)*N$6 -> 95.039691 | O46: =(Inputs!$I$30*Inputs!$K$30+Inputs!$J$30*Inputs!$L$30)*ScenMult*(1+Inputs!$M$30)^(O$4-1)*O$6 -> 93.614096 | P46: =(Inputs!$I$30*Inputs!$K$30+Inputs!$J$30*Inputs!$L$30)*ScenMult*(1+Inputs!$M$30)^(P$4-1)*P$6 -> 92.209885 | ... W46: =(Inputs!$I$30*Inputs!$K$30+Inputs!$J$30*Inputs!$L$30)*ScenMult*(1+Inputs!$M$30)^(W$4-1)*W$6 -> 82.952808
C47: =Inputs!$C$31 -> SE-WN1 | D47: =Inputs!$D$31 -> Sweden (SE3) | E47: =Inputs!$E$31 -> Onshore wind | F47: EUR/MWh | G47: =IF(G23=0,0,G83*1000/G23) -> 46.609643 | I47: =(Inputs!$I$31*Inputs!$K$31+Inputs!$J$31*Inputs!$L$31)*ScenMult*(1+Inputs!$M$31)^(I$4-1)*I$6 -> 45 | J47: =(Inputs!$I$31*Inputs!$K$31+Inputs!$J$31*Inputs!$L$31)*ScenMult*(1+Inputs!$M$31)^(J$4-1)*J$6 -> 45.225 | K47: =(Inputs!$I$31*Inputs!$K$31+Inputs!$J$31*Inputs!$L$31)*ScenMult*(1+Inputs!$M$31)^(K$4-1)*K$6 -> 45.451125 | L47: =(Inputs!$I$31*Inputs!$K$31+Inputs!$J$31*Inputs!$L$31)*ScenMult*(1+Inputs!$M$31)^(L$4-1)*L$6 -> 45.678381 | M47: =(Inputs!$I$31*Inputs!$K$31+Inputs!$J$31*Inputs!$L$31)*ScenMult*(1+Inputs!$M$31)^(M$4-1)*M$6 -> 45.906773 | N47: =(Inputs!$I$31*Inputs!$K$31+Inputs!$J$31*Inputs!$L$31)*ScenMult*(1+Inputs!$M$31)^(N$4-1)*N$6 -> 46.136306 | O47: =(Inputs!$I$31*Inputs!$K$31+Inputs!$J$31*Inputs!$L$31)*ScenMult*(1+Inputs!$M$31)^(O$4-1)*O$6 -> 46.366988 | P47: =(Inputs!$I$31*Inputs!$K$31+Inputs!$J$31*Inputs!$L$31)*ScenMult*(1+Inputs!$M$31)^(P$4-1)*P$6 -> 46.598823 | ... W47: =(Inputs!$I$31*Inputs!$K$31+Inputs!$J$31*Inputs!$L$31)*ScenMult*(1+Inputs!$M$31)^(W$4-1)*W$6 -> 48.254451
C48: =Inputs!$C$32 -> FI-WN1 | D48: =Inputs!$D$32 -> Finland | E48: =Inputs!$E$32 -> Onshore wind | F48: EUR/MWh | G48: =IF(G24=0,0,G84*1000/G24) -> 41.982494 | I48: =(Inputs!$I$32*Inputs!$K$32+Inputs!$J$32*Inputs!$L$32)*ScenMult*(1+Inputs!$M$32)^(I$4-1)*I$6 -> 45 | J48: =(Inputs!$I$32*Inputs!$K$32+Inputs!$J$32*Inputs!$L$32)*ScenMult*(1+Inputs!$M$32)^(J$4-1)*J$6 -> 44.55 | K48: =(Inputs!$I$32*Inputs!$K$32+Inputs!$J$32*Inputs!$L$32)*ScenMult*(1+Inputs!$M$32)^(K$4-1)*K$6 -> 44.1045 | L48: =(Inputs!$I$32*Inputs!$K$32+Inputs!$J$32*Inputs!$L$32)*ScenMult*(1+Inputs!$M$32)^(L$4-1)*L$6 -> 43.663455 | M48: =(Inputs!$I$32*Inputs!$K$32+Inputs!$J$32*Inputs!$L$32)*ScenMult*(1+Inputs!$M$32)^(M$4-1)*M$6 -> 43.22682 | N48: =(Inputs!$I$32*Inputs!$K$32+Inputs!$J$32*Inputs!$L$32)*ScenMult*(1+Inputs!$M$32)^(N$4-1)*N$6 -> 42.794552 | O48: =(Inputs!$I$32*Inputs!$K$32+Inputs!$J$32*Inputs!$L$32)*ScenMult*(1+Inputs!$M$32)^(O$4-1)*O$6 -> 42.366607 | P48: =(Inputs!$I$32*Inputs!$K$32+Inputs!$J$32*Inputs!$L$32)*ScenMult*(1+Inputs!$M$32)^(P$4-1)*P$6 -> 41.942941 | ... W48: =(Inputs!$I$32*Inputs!$K$32+Inputs!$J$32*Inputs!$L$32)*ScenMult*(1+Inputs!$M$32)^(W$4-1)*W$6 -> 39.093562
B50: =+B38+1 -> 5 | C50: PPA strike price (indexed)
C51: =Inputs!$C$23 -> ES-PV1 | D51: =Inputs!$D$23 -> Spain | E51: =Inputs!$E$23 -> Solar PV | F51: EUR/MWh | G51: =IF(G15=0,0,G87*1000/G15) -> 40.740861 | I51: =Inputs!$N$23*(1+Inputs!$O$23)^(I$4-1)*I$6 -> 38 | J51: =Inputs!$N$23*(1+Inputs!$O$23)^(J$4-1)*J$6 -> 38.38 | K51: =Inputs!$N$23*(1+Inputs!$O$23)^(K$4-1)*K$6 -> 38.7638 | L51: =Inputs!$N$23*(1+Inputs!$O$23)^(L$4-1)*L$6 -> 39.151438 | M51: 38 | N51: =Inputs!$N$23*(1+Inputs!$O$23)^(N$4-1)*N$6 -> 39.938382 | O51: =Inputs!$N$23*(1+Inputs!$O$23)^(O$4-1)*O$6 -> 40.337766 | P51: =Inputs!$N$23*(1+Inputs!$O$23)^(P$4-1)*P$6 -> 40.741143 | Q51: =Inputs!$N$23*(1+Inputs!$O$23)^(Q$4-1)*Q$6 -> 41.148555 | R51: =Inputs!$N$23*(1+Inputs!$O$23)^(R$4-1)*R$6 -> 41.56004 | S51: =Inputs!$N$23*(1+Inputs!$O$23)^(S$4-1)*S$6 -> 41.975641 | T51: =Inputs!$N$23*(1+Inputs!$O$23)^(T$4-1)*T$6 -> 42.395397 | U51: =Inputs!$N$23*(1+Inputs!$O$23)^(U$4-1)*U$6 -> 42.819351 | ... W51: =Inputs!$N$23*(1+Inputs!$O$23)^(W$4-1)*W$6 -> 43.68002
C52: =Inputs!$C$24 -> PT-PV1 | D52: =Inputs!$D$24 -> Portugal | E52: =Inputs!$E$24 -> Solar PV | F52: EUR/MWh | G52: =IF(G16=0,0,G88*1000/G16) -> 42.885116 | I52: =Inputs!$N$24*(1+Inputs!$O$24)^(I$4-1)*I$6 -> 40 | J52: =Inputs!$N$24*(1+Inputs!$O$24)^(J$4-1)*J$6 -> 40.4 | K52: =Inputs!$N$24*(1+Inputs!$O$24)^(K$4-1)*K$6 -> 40.804 | L52: =Inputs!$N$24*(1+Inputs!$O$24)^(L$4-1)*L$6 -> 41.21204 | M52: =Inputs!$N$24*(1+Inputs!$O$24)^(M$4-1)*M$6 -> 41.62416 | N52: =Inputs!$N$24*(1+Inputs!$O$24)^(N$4-1)*N$6 -> 42.040402 | O52: =Inputs!$N$24*(1+Inputs!$O$24)^(O$4-1)*O$6 -> 42.460806 | P52: =Inputs!$N$24*(1+Inputs!$O$24)^(P$4-1)*P$6 -> 42.885414 | ... W52: =Inputs!$N$24*(1+Inputs!$O$24)^(W$4-1)*W$6 -> 45.978969
C53: =Inputs!$C$25 -> IT-PV1 | D53: =Inputs!$D$25 -> Italy (Sud) | E53: =Inputs!$E$25 -> Solar PV | F53: EUR/MWh | G53: =IF(G17=0,0,G89*1000/G17) -> 78 | I53: =Inputs!$N$25*(1+Inputs!$O$25)^(I$4-1)*I$6 -> 78 | J53: =Inputs!$N$25*(1+Inputs!$O$25)^(J$4-1)*J$6 -> 78 | K53: =Inputs!$N$25*(1+Inputs!$O$25)^(K$4-1)*K$6 -> 78 | L53: =Inputs!$N$25*(1+Inputs!$O$25)^(L$4-1)*L$6 -> 78 | M53: =Inputs!$N$25*(1+Inputs!$O$25)^(M$4-1)*M$6 -> 78 | N53: =Inputs!$N$25*(1+Inputs!$O$25)^(N$4-1)*N$6 -> 78 | O53: =Inputs!$N$25*(1+Inputs!$O$25)^(O$4-1)*O$6 -> 78 | P53: =Inputs!$N$25*(1+Inputs!$O$25)^(P$4-1)*P$6 -> 78 | ... W53: =Inputs!$N$25*(1+Inputs!$O$25)^(W$4-1)*W$6 -> 78
C54: =Inputs!$C$26 -> GR-PV1 | D54: =Inputs!$D$26 -> Greece | E54: =Inputs!$E$26 -> Solar PV | F54: EUR/MWh | G54: =IF(G18=0,0,G90*1000/G18) -> 60.046623 | I54: =Inputs!$N$26*(1+Inputs!$O$26)^(I$4-1)*I$6 -> 58 | J54: =Inputs!$N$26*(1+Inputs!$O$26)^(J$4-1)*J$6 -> 58.29 | K54: =Inputs!$N$26*(1+Inputs!$O$26)^(K$4-1)*K$6 -> 58.58145 | L54: =Inputs!$N$26*(1+Inputs!$O$26)^(L$4-1)*L$6 -> 58.874357 | M54: =Inputs!$N$26*(1+Inputs!$O$26)^(M$4-1)*M$6 -> 59.168729 | N54: =Inputs!$N$26*(1+Inputs!$O$26)^(N$4-1)*N$6 -> 59.464573 | O54: =Inputs!$N$26*(1+Inputs!$O$26)^(O$4-1)*O$6 -> 59.761896 | P54: =Inputs!$N$26*(1+Inputs!$O$26)^(P$4-1)*P$6 -> 60.060705 | ... W54: =Inputs!$N$26*(1+Inputs!$O$26)^(W$4-1)*W$6 -> 62.194626
C55: =Inputs!$C$27 -> FR-WN1 | D55: =Inputs!$D$27 -> France | E55: =Inputs!$E$27 -> Onshore wind | F55: EUR/MWh | G55: =IF(G19=0,0,G91*1000/G19) -> 68.680088 | I55: =Inputs!$N$27*(1+Inputs!$O$27)^(I$4-1)*I$6 -> 64 | J55: =Inputs!$N$27*(1+Inputs!$O$27)^(J$4-1)*J$6 -> 64.64 | K55: =Inputs!$N$27*(1+Inputs!$O$27)^(K$4-1)*K$6 -> 65.2864 | L55: =Inputs!$N$27*(1+Inputs!$O$27)^(L$4-1)*L$6 -> 65.939264 | M55: =Inputs!$N$27*(1+Inputs!$O$27)^(M$4-1)*M$6 -> 66.598657 | N55: =Inputs!$N$27*(1+Inputs!$O$27)^(N$4-1)*N$6 -> 67.264643 | O55: =Inputs!$N$27*(1+Inputs!$O$27)^(O$4-1)*O$6 -> 67.93729 | P55: =Inputs!$N$27*(1+Inputs!$O$27)^(P$4-1)*P$6 -> 68.616663 | ... W55: =Inputs!$N$27*(1+Inputs!$O$27)^(W$4-1)*W$6 -> 73.56635
C56: =Inputs!$C$28 -> DE-WN1 | D56: =Inputs!$D$28 -> Germany | E56: =Inputs!$E$28 -> Onshore wind | F56: EUR/MWh | G56: =IF(G20=0,0,G92*1000/G20) -> 77.265099 | I56: =Inputs!$N$28*(1+Inputs!$O$28)^(I$4-1)*I$6 -> 72 | J56: =Inputs!$N$28*(1+Inputs!$O$28)^(J$4-1)*J$6 -> 72.72 | K56: =Inputs!$N$28*(1+Inputs!$O$28)^(K$4-1)*K$6 -> 73.4472 | L56: =Inputs!$N$28*(1+Inputs!$O$28)^(L$4-1)*L$6 -> 74.181672 | M56: =Inputs!$N$28*(1+Inputs!$O$28)^(M$4-1)*M$6 -> 74.923489 | N56: =Inputs!$N$28*(1+Inputs!$O$28)^(N$4-1)*N$6 -> 75.672724 | O56: =Inputs!$N$28*(1+Inputs!$O$28)^(O$4-1)*O$6 -> 76.429451 | P56: =Inputs!$N$28*(1+Inputs!$O$28)^(P$4-1)*P$6 -> 77.193745 | ... W56: =Inputs!$N$28*(1+Inputs!$O$28)^(W$4-1)*W$6 -> 82.762143
C57: =Inputs!$C$29 -> NL-OW1 | D57: =Inputs!$D$29 -> Netherlands | E57: =Inputs!$E$29 -> Offshore wind | F57: EUR/MWh | G57: =IF(G21=0,0,G93*1000/G21) -> 88.971401 | I57: =Inputs!$N$29*(1+Inputs!$O$29)^(I$4-1)*I$6 -> 80 | J57: =Inputs!$N$29*(1+Inputs!$O$29)^(J$4-1)*J$6 -> 81.2 | K57: =Inputs!$N$29*(1+Inputs!$O$29)^(K$4-1)*K$6 -> 82.418 | L57: =Inputs!$N$29*(1+Inputs!$O$29)^(L$4-1)*L$6 -> 83.65427 | M57: =Inputs!$N$29*(1+Inputs!$O$29)^(M$4-1)*M$6 -> 84.909084 | N57: =Inputs!$N$29*(1+Inputs!$O$29)^(N$4-1)*N$6 -> 86.18272 | O57: =Inputs!$N$29*(1+Inputs!$O$29)^(O$4-1)*O$6 -> 87.475461 | P57: =Inputs!$N$29*(1+Inputs!$O$29)^(P$4-1)*P$6 -> 88.787593 | ... W57: =Inputs!$N$29*(1+Inputs!$O$29)^(W$4-1)*W$6 -> 98.540458
C58: =Inputs!$C$30 -> PL-WN1 | D58: =Inputs!$D$30 -> Poland | E58: =Inputs!$E$30 -> Onshore wind | F58: EUR/MWh | G58: =IF(G22=0,0,G94*1000/G22) -> 87.996362 | I58: =Inputs!$N$30*(1+Inputs!$O$30)^(I$4-1)*I$6 -> 82 | J58: =Inputs!$N$30*(1+Inputs!$O$30)^(J$4-1)*J$6 -> 82.82 | K58: =Inputs!$N$30*(1+Inputs!$O$30)^(K$4-1)*K$6 -> 83.6482 | L58: =Inputs!$N$30*(1+Inputs!$O$30)^(L$4-1)*L$6 -> 84.484682 | M58: =Inputs!$N$30*(1+Inputs!$O$30)^(M$4-1)*M$6 -> 85.329529 | N58: =Inputs!$N$30*(1+Inputs!$O$30)^(N$4-1)*N$6 -> 86.182824 | O58: =Inputs!$N$30*(1+Inputs!$O$30)^(O$4-1)*O$6 -> 87.044652 | P58: =Inputs!$N$30*(1+Inputs!$O$30)^(P$4-1)*P$6 -> 87.915099 | ... W58: =Inputs!$N$30*(1+Inputs!$O$30)^(W$4-1)*W$6 -> 94.256885
C59: =Inputs!$C$31 -> SE-WN1 | D59: =Inputs!$D$31 -> Sweden (SE3) | E59: =Inputs!$E$31 -> Onshore wind | F59: EUR/MWh | G59: =IF(G23=0,0,G95*1000/G23) -> 38.632549 | I59: =Inputs!$N$31*(1+Inputs!$O$31)^(I$4-1)*I$6 -> 36 | J59: =Inputs!$N$31*(1+Inputs!$O$31)^(J$4-1)*J$6 -> 36.36 | K59: =Inputs!$N$31*(1+Inputs!$O$31)^(K$4-1)*K$6 -> 36.7236 | L59: =Inputs!$N$31*(1+Inputs!$O$31)^(L$4-1)*L$6 -> 37.090836 | M59: =Inputs!$N$31*(1+Inputs!$O$31)^(M$4-1)*M$6 -> 37.461744 | N59: =Inputs!$N$31*(1+Inputs!$O$31)^(N$4-1)*N$6 -> 37.836362 | O59: =Inputs!$N$31*(1+Inputs!$O$31)^(O$4-1)*O$6 -> 38.214725 | P59: =Inputs!$N$31*(1+Inputs!$O$31)^(P$4-1)*P$6 -> 38.596873 | ... W59: =Inputs!$N$31*(1+Inputs!$O$31)^(W$4-1)*W$6 -> 41.381072
C60: =Inputs!$C$32 -> FI-WN1 | D60: =Inputs!$D$32 -> Finland | E60: =Inputs!$E$32 -> Onshore wind | F60: EUR/MWh | G60: =IF(G24=0,0,G96*1000/G24) -> 40.778802 | I60: =Inputs!$N$32*(1+Inputs!$O$32)^(I$4-1)*I$6 -> 38 | J60: =Inputs!$N$32*(1+Inputs!$O$32)^(J$4-1)*J$6 -> 38.38 | K60: =Inputs!$N$32*(1+Inputs!$O$32)^(K$4-1)*K$6 -> 38.7638 | L60: =Inputs!$N$32*(1+Inputs!$O$32)^(L$4-1)*L$6 -> 39.151438 | M60: =Inputs!$N$32*(1+Inputs!$O$32)^(M$4-1)*M$6 -> 39.542952 | N60: =Inputs!$N$32*(1+Inputs!$O$32)^(N$4-1)*N$6 -> 39.938382 | O60: =Inputs!$N$32*(1+Inputs!$O$32)^(O$4-1)*O$6 -> 40.337766 | P60: =Inputs!$N$32*(1+Inputs!$O$32)^(P$4-1)*P$6 -> 40.741143 | ... W60: =Inputs!$N$32*(1+Inputs!$O$32)^(W$4-1)*W$6 -> 43.68002
B62: =+B50+1 -> 6 | C62: Settlement spread (capture - strike)
C63: =Inputs!$C$23 -> ES-PV1 | D63: =Inputs!$D$23 -> Spain | E63: =Inputs!$E$23 -> Solar PV | F63: EUR/MWh | G63: =G39-G51 -> 10.432551 | I63: =I39-I51 -> 16.8 | J63: =J39-J51 -> 15.872 | K63: =K39-K51 -> 14.94568 | L63: =L39-L51 -> 14.020947 | M63: =M39-M51 -> 13.097709 | N63: =N39-N51 -> 12.175873 | O63: =O39-O51 -> 11.255346 | P63: =P39-P51 -> 10.336038 | ... W63: =W39-W51 -> 3.9272504
C64: =Inputs!$C$24 -> PT-PV1 | D64: =Inputs!$D$24 -> Portugal | E64: =Inputs!$E$24 -> Solar PV | F64: EUR/MWh | G64: =G40-G52 -> 7.5412378 | I64: =I40-I52 -> 14 | J64: =J40-J52 -> 13.06 | K64: =K40-K52 -> 12.1214 | L64: =L40-L52 -> 11.184106 | M64: =M40-M52 -> 10.248024 | N64: =N40-N52 -> 9.3130607 | O64: =O40-O52 -> 8.379122 | P64: =P40-P52 -> 7.4461147 | ... W64: =W40-W52 -> 0.93330536
C65: =Inputs!$C$25 -> IT-PV1 | D65: =Inputs!$D$25 -> Italy (Sud) | E65: =Inputs!$E$25 -> Solar PV | F65: EUR/MWh | G65: =G41-G53 -> 11.087127 | I65: =I41-I53 -> 31 | J65: =J41-J53 -> 27.73 | K65: =K41-K53 -> 24.5581 | L65: =L41-L53 -> 21.481357 | M65: =M41-M53 -> 18.496916 | N65: =N41-N53 -> 15.602009 | O65: =O41-O53 -> 12.793949 | P65: =P41-P53 -> 10.07013 | ... W65: =W41-W53 -> -6.8408458
C66: =Inputs!$C$26 -> GR-PV1 | D66: =Inputs!$D$26 -> Greece | E66: =Inputs!$E$26 -> Solar PV | F66: EUR/MWh | G66: =G42-G54 -> 20.800728 | I66: =I42-I54 -> 34.6 | J66: =J42-J54 -> 32.458 | K66: =K42-K54 -> 30.35159 | L66: =L42-L54 -> 28.280022 | M66: =M42-M54 -> 26.242563 | N66: =N42-N54 -> 24.238493 | O66: =O42-O54 -> 22.267109 | P66: =P42-P54 -> 20.327719 | ... W66: =W42-W54 -> 7.5926181
C67: =Inputs!$C$27 -> FR-WN1 | D67: =Inputs!$D$27 -> France | E67: =Inputs!$E$27 -> Onshore wind | F67: EUR/MWh | G67: =G43-G55 -> -1.0731264 | I67: =I43-I55 -> -1 | J67: =J43-J55 -> -1.01 | K67: =K43-K55 -> -1.0201 | L67: =L43-L55 -> -1.030301 | M67: =M43-M55 -> -1.040604 | N67: =N43-N55 -> -1.0510101 | O67: =O43-O55 -> -1.0615202 | P67: =P43-P55 -> -1.0721354 | ... W67: =W43-W55 -> -1.1494742
C68: =Inputs!$C$28 -> DE-WN1 | D68: =Inputs!$D$28 -> Germany | E68: =Inputs!$E$28 -> Onshore wind | F68: EUR/MWh | G68: =G44-G56 -> 0.9604151 | I68: =I44-I56 -> 9 | J68: =J44-J56 -> 7.875 | K68: =K44-K56 -> 6.744825 | L68: =L44-L56 -> 5.6093929 | M68: =M44-M56 -> 4.4686208 | N68: =N44-N56 -> 3.3224254 | O68: =O44-O56 -> 2.1707224 | P68: =P44-P56 -> 1.013427 | ... W68: =W44-W56 -> -7.2515037
C69: =Inputs!$C$29 -> NL-OW1 | D69: =Inputs!$D$29 -> Netherlands | E69: =Inputs!$E$29 -> Offshore wind | F69: EUR/MWh | G69: =G45-G57 -> -8.9714015 | I69: =I45-I57 -> 0 | J69: =J45-J57 -> -1.2 | K69: =K45-K57 -> -2.418 | L69: =L45-L57 -> -3.65427 | M69: =M45-M57 -> -4.909084 | N69: =N45-N57 -> -6.1827203 | O69: =O45-O57 -> -7.4754611 | P69: =P45-P57 -> -8.787593 | ... W69: =W45-W57 -> -18.540458
C70: =Inputs!$C$30 -> PL-WN1 | D70: =Inputs!$D$30 -> Poland | E70: =Inputs!$E$30 -> Onshore wind | F70: EUR/MWh | G70: =G46-G58 -> 4.4102333 | I70: =I46-I58 -> 20.5 | J70: =J46-J58 -> 18.1425 | K70: =K46-K58 -> 15.799863 | L70: =L46-L58 -> 13.47166 | M70: =M46-M58 -> 11.157468 | N70: =N46-N58 -> 8.8568674 | O70: =O46-O58 -> 6.5694438 | P70: =P46-P58 -> 4.2947858 | ... W70: =W46-W58 -> -11.304077
C71: =Inputs!$C$31 -> SE-WN1 | D71: =Inputs!$D$31 -> Sweden (SE3) | E71: =Inputs!$E$31 -> Onshore wind | F71: EUR/MWh | G71: =G47-G59 -> 7.9770933 | I71: =I47-I59 -> 9 | J71: =J47-J59 -> 8.865 | K71: =K47-K59 -> 8.727525 | L71: =L47-L59 -> 8.5875446 | M71: =M47-M59 -> 8.4450282 | N71: =N47-N59 -> 8.2999446 | O71: =O47-O59 -> 8.1522625 | P71: =P47-P59 -> 8.0019502 | ... W71: =W47-W59 -> 6.8733793
C72: =Inputs!$C$32 -> FI-WN1 | D72: =Inputs!$D$32 -> Finland | E72: =Inputs!$E$32 -> Onshore wind | F72: EUR/MWh | G72: =G48-G60 -> 1.2036916 | I72: =I48-I60 -> 7 | J72: =J48-J60 -> 6.17 | K72: =K48-K60 -> 5.3407 | L72: =L48-L60 -> 4.512017 | M72: =M48-M60 -> 3.6838681 | N72: =N48-N60 -> 2.8561703 | O72: =O48-O60 -> 2.028841 | P72: =P48-P60 -> 1.2017973 | ... W72: =W48-W60 -> -4.5864585
B74: =+B62+1 -> 7 | C74: Market value of generation
C75: =Inputs!$C$23 -> ES-PV1 | D75: =Inputs!$D$23 -> Spain | E75: =Inputs!$E$23 -> Solar PV | F75: EUR k | G75: =SUM(I75:W75) -> 129552.57 | I75: =I15*I39/1000 -> 9576.9576 | J75: =J15*J39/1000 -> 9433.7821 | K75: =K15*K39/1000 -> 9292.747 | L75: =L15*L39/1000 -> 9153.8205 | M75: =M15*M39/1000 -> 9016.9709 | N75: =N15*N39/1000 -> 8882.1671 | O75: =O15*O39/1000 -> 8749.3787 | P75: =P15*P39/1000 -> 8618.5755 | ... W75: =W15*W39/1000 -> 7756.1004
C76: =Inputs!$C$24 -> PT-PV1 | D76: =Inputs!$D$24 -> Portugal | E76: =Inputs!$E$24 -> Solar PV | F76: EUR k | G76: =SUM(I76:W76) -> 89586.873 | I76: =I16*I40/1000 -> 6622.56 | J76: =J16*J40/1000 -> 6523.5527 | K76: =K16*K40/1000 -> 6426.0256 | L76: =L16*L40/1000 -> 6329.9565 | M76: =M16*M40/1000 -> 6235.3237 | N76: =N16*N40/1000 -> 6142.1056 | O76: =O16*O40/1000 -> 6050.2811 | P76: =P16*P40/1000 -> 5959.8294 | ... W76: =W16*W40/1000 -> 5363.4194
C77: =Inputs!$C$25 -> IT-PV1 | D77: =Inputs!$D$25 -> Italy (Sud) | E77: =Inputs!$E$25 -> Solar PV | F77: EUR k | G77: =SUM(I77:W77) -> 162793.18 | I77: =I17*I41/1000 -> 13749.696 | J77: =J17*J41/1000 -> 13270.519 | K77: =K17*K41/1000 -> 12808.042 | L77: =L17*L41/1000 -> 12361.681 | M77: =M17*M41/1000 -> 11930.877 | N77: =N17*N41/1000 -> 11515.086 | O77: =O17*O41/1000 -> 11113.785 | P77: =P17*P41/1000 -> 10726.469 | ... W77: =W17*W41/1000 -> 8367.9775
C78: =Inputs!$C$26 -> GR-PV1 | D78: =Inputs!$D$26 -> Greece | E78: =Inputs!$E$26 -> Solar PV | F78: EUR k | G78: =SUM(I78:W78) -> 153891.92 | I78: =I18*I42/1000 -> 12167.64 | J78: =J18*J42/1000 -> 11864.666 | K78: =K18*K42/1000 -> 11569.236 | L78: =L18*L42/1000 -> 11281.162 | M78: =M18*M42/1000 -> 11000.261 | N78: =N18*N42/1000 -> 10726.354 | O78: =O18*O42/1000 -> 10459.268 | P78: =P18*P42/1000 -> 10198.832 | ... W78: =W18*W42/1000 -> 8548.5911
C79: =Inputs!$C$27 -> FR-WN1 | D79: =Inputs!$D$27 -> France | E79: =Inputs!$E$27 -> Onshore wind | F79: EUR k | G79: =SUM(I79:W79) -> 133253.32 | I79: =I19*I43/1000 -> 8278.2 | J79: =J19*J43/1000 -> 8360.982 | K79: =K19*K43/1000 -> 8444.5918 | L79: =L19*L43/1000 -> 8529.0377 | M79: =M19*M43/1000 -> 8614.3281 | N79: =N19*N43/1000 -> 8700.4714 | O79: =O19*O43/1000 -> 8787.4761 | P79: =P19*P43/1000 -> 8875.3509 | ... W79: =W19*W43/1000 -> 9515.5774
C80: =Inputs!$C$28 -> DE-WN1 | D80: =Inputs!$D$28 -> Germany | E80: =Inputs!$E$28 -> Onshore wind | F80: EUR k | G80: =SUM(I80:W80) -> 160349.79 | I80: =I20*I44/1000 -> 11069.136 | J80: =J20*J44/1000 -> 11013.79 | K80: =K20*K44/1000 -> 10958.721 | L80: =L20*L44/1000 -> 10903.928 | M80: =M20*M44/1000 -> 10849.408 | N80: =N20*N44/1000 -> 10795.161 | O80: =O20*O44/1000 -> 10741.185 | P80: =P20*P44/1000 -> 10687.479 | ... W80: =W20*W44/1000 -> 10318.982
C81: =Inputs!$C$29 -> NL-OW1 | D81: =Inputs!$D$29 -> Netherlands | E81: =Inputs!$E$29 -> Offshore wind | F81: EUR k | G81: =SUM(I81:W81) -> 198676.8 | I81: =I21*I45/1000 -> 13245.12 | J81: =J21*J45/1000 -> 13245.12 | K81: =K21*K45/1000 -> 13245.12 | L81: =L21*L45/1000 -> 13245.12 | M81: =M21*M45/1000 -> 13245.12 | N81: =N21*N45/1000 -> 13245.12 | O81: =O21*O45/1000 -> 13245.12 | P81: =P21*P45/1000 -> 13245.12 | ... W81: =W21*W45/1000 -> 13245.12
C82: =Inputs!$C$30 -> PL-WN1 | D82: =Inputs!$D$30 -> Poland | E82: =Inputs!$E$30 -> Onshore wind | F82: EUR k | G82: =SUM(I82:W82) -> 200346.74 | I82: =I22*I46/1000 -> 14815.35 | J82: =J22*J46/1000 -> 14593.12 | K82: =K22*K46/1000 -> 14374.223 | L82: =L22*L46/1000 -> 14158.61 | M82: =M22*M46/1000 -> 13946.23 | N82: =N22*N46/1000 -> 13737.037 | O82: =O22*O46/1000 -> 13530.981 | P82: =P22*P46/1000 -> 13328.017 | ... W82: =W22*W46/1000 -> 11989.999
C83: =Inputs!$C$31 -> SE-WN1 | D83: =Inputs!$D$31 -> Sweden (SE3) | E83: =Inputs!$E$31 -> Onshore wind | F83: EUR k | G83: =SUM(I83:W83) -> 121265.24 | I83: =I23*I47/1000 -> 7805.16 | J83: =J23*J47/1000 -> 7844.1858 | K83: =K23*K47/1000 -> 7883.4067 | L83: =L23*L47/1000 -> 7922.8238 | M83: =M23*M47/1000 -> 7962.4379 | N83: =N23*N47/1000 -> 8002.2501 | O83: =O23*O47/1000 -> 8042.2613 | P83: =P23*P47/1000 -> 8082.4726 | ... W83: =W23*W47/1000 -> 8369.638
C84: =Inputs!$C$32 -> FI-WN1 | D84: =Inputs!$D$32 -> Finland | E84: =Inputs!$E$32 -> Onshore wind | F84: EUR k | G84: =SUM(I84:W84) -> 96538.744 | I84: =I24*I48/1000 -> 6898.5 | J84: =J24*J48/1000 -> 6829.515 | K84: =K24*K48/1000 -> 6761.2199 | L84: =L24*L48/1000 -> 6693.6077 | M84: =M24*M48/1000 -> 6626.6716 | N84: =N24*N48/1000 -> 6560.4049 | O84: =O24*O48/1000 -> 6494.8008 | P84: =P24*P48/1000 -> 6429.8528 | ... W84: =W24*W48/1000 -> 5993.043
B86: =+B74+1 -> 8 | C86: PPA strike payment
C87: =Inputs!$C$23 -> ES-PV1 | D87: =Inputs!$D$23 -> Spain | E87: =Inputs!$E$23 -> Solar PV | F87: EUR k | G87: =SUM(I87:W87) -> 103141.13 | I87: =I15*I51/1000 -> 6640.956 | J87: =J15*J51/1000 -> 6673.8287 | K87: =K15*K51/1000 -> 6706.8642 | L87: =L15*L51/1000 -> 6740.0632 | M87: =M15*M51/1000 -> 6773.4265 | N87: =N15*N51/1000 -> 6806.9549 | O87: =O15*O51/1000 -> 6840.6494 | P87: =P15*P51/1000 -> 6874.5106 | ... W87: =W15*W51/1000 -> 7116.279
C88: =Inputs!$C$24 -> PT-PV1 | D88: =Inputs!$D$24 -> Portugal | E88: =Inputs!$E$24 -> Solar PV | F88: EUR k | G88: =SUM(I88:W88) -> 76189.197 | I88: =I16*I52/1000 -> 4905.6 | J88: =J16*J52/1000 -> 4929.8827 | K88: =K16*K52/1000 -> 4954.2856 | L88: =L16*L52/1000 -> 4978.8094 | M88: =M16*M52/1000 -> 5003.4545 | N88: =N16*N52/1000 -> 5028.2216 | O88: =O16*O52/1000 -> 5053.1113 | P88: =P16*P52/1000 -> 5078.1242 | ... W88: =W16*W52/1000 -> 5256.7158
C89: =Inputs!$C$25 -> IT-PV1 | D89: =Inputs!$D$25 -> Italy (Sud) | E89: =Inputs!$E$25 -> Solar PV | F89: EUR k | G89: =SUM(I89:W89) -> 142533.14 | I89: =I17*I53/1000 -> 9839.232 | J89: =J17*J53/1000 -> 9790.0358 | K89: =K17*K53/1000 -> 9741.0857 | L89: =L17*L53/1000 -> 9692.3802 | M89: =M17*M53/1000 -> 9643.9183 | N89: =N17*N53/1000 -> 9595.6987 | O89: =O17*O53/1000 -> 9547.7202 | P89: =P17*P53/1000 -> 9499.9816 | ... W89: =W17*W53/1000 -> 9172.4284
C90: =Inputs!$C$26 -> GR-PV1 | D90: =Inputs!$D$26 -> Greece | E90: =Inputs!$E$26 -> Solar PV | F90: EUR k | G90: =SUM(I90:W90) -> 114298 | I90: =I18*I54/1000 -> 7621.2 | J90: =J18*J54/1000 -> 7621.0095 | K90: =K18*K54/1000 -> 7620.8189 | L90: =L18*L54/1000 -> 7620.6284 | M90: =M18*M54/1000 -> 7620.4379 | N90: =N18*N54/1000 -> 7620.2474 | O90: =O18*O54/1000 -> 7620.0569 | P90: =P18*P54/1000 -> 7619.8664 | ... W90: =W18*W54/1000 -> 7618.533
C91: =Inputs!$C$27 -> FR-WN1 | D91: =Inputs!$D$27 -> France | E91: =Inputs!$E$27 -> Onshore wind | F91: EUR k | G91: =SUM(I91:W91) -> 135368.45 | I91: =I19*I55/1000 -> 8409.6 | J91: =J19*J55/1000 -> 8493.696 | K91: =K19*K55/1000 -> 8578.633 | L91: =L19*L55/1000 -> 8664.4193 | M91: =M19*M55/1000 -> 8751.0635 | N91: =N19*N55/1000 -> 8838.5741 | O91: =O19*O55/1000 -> 8926.9599 | P91: =P19*P55/1000 -> 9016.2295 | ... W91: =W19*W55/1000 -> 9666.6183
C92: =Inputs!$C$28 -> DE-WN1 | D92: =Inputs!$D$28 -> Germany | E92: =Inputs!$E$28 -> Onshore wind | F92: EUR k | G92: =SUM(I92:W92) -> 158381.09 | I92: =I20*I56/1000 -> 9839.232 | J92: =J20*J56/1000 -> 9937.6243 | K92: =K20*K56/1000 -> 10037.001 | L92: =L20*L56/1000 -> 10137.371 | M92: =M20*M56/1000 -> 10238.744 | N92: =N20*N56/1000 -> 10341.132 | O92: =O20*O56/1000 -> 10444.543 | P92: =P20*P56/1000 -> 10548.988 | ... W92: =W20*W56/1000 -> 11309.943
C93: =Inputs!$C$29 -> NL-OW1 | D93: =Inputs!$D$29 -> Netherlands | E93: =Inputs!$E$29 -> Offshore wind | F93: EUR k | G93: =SUM(I93:W93) -> 220956.92 | I93: =I21*I57/1000 -> 13245.12 | J93: =J21*J57/1000 -> 13443.797 | K93: =K21*K57/1000 -> 13645.454 | L93: =L21*L57/1000 -> 13850.136 | M93: =M21*M57/1000 -> 14057.888 | N93: =N21*N57/1000 -> 14268.756 | O93: =O21*O57/1000 -> 14482.787 | P93: =P21*P57/1000 -> 14700.029 | ... W93: =W21*W57/1000 -> 16314.752
C94: =Inputs!$C$30 -> PL-WN1 | D94: =Inputs!$D$30 -> Poland | E94: =Inputs!$E$30 -> Onshore wind | F94: EUR k | G94: =SUM(I94:W94) -> 190784.91 | I94: =I22*I58/1000 -> 11852.28 | J94: =J22*J58/1000 -> 11970.803 | K94: =K22*K58/1000 -> 12090.511 | L94: =L22*L58/1000 -> 12211.416 | M94: =M22*M58/1000 -> 12333.53 | N94: =N22*N58/1000 -> 12456.865 | O94: =O22*O58/1000 -> 12581.434 | P94: =P22*P58/1000 -> 12707.248 | ... W94: =W22*W58/1000 -> 13623.89
C95: =Inputs!$C$31 -> SE-WN1 | D95: =Inputs!$D$31 -> Sweden (SE3) | E95: =Inputs!$E$31 -> Onshore wind | F95: EUR k | G95: =SUM(I95:W95) -> 100511.08 | I95: =I23*I59/1000 -> 6244.128 | J95: =J23*J59/1000 -> 6306.5693 | K95: =K23*K59/1000 -> 6369.635 | L95: =L23*L59/1000 -> 6433.3313 | M95: =M23*M59/1000 -> 6497.6646 | N95: =N23*N59/1000 -> 6562.6413 | O95: =O23*O59/1000 -> 6628.2677 | P95: =P23*P59/1000 -> 6694.5504 | ... W95: =W23*W59/1000 -> 7177.4641
C96: =Inputs!$C$32 -> FI-WN1 | D96: =Inputs!$D$32 -> Finland | E96: =Inputs!$E$32 -> Onshore wind | F96: EUR k | G96: =SUM(I96:W96) -> 93770.855 | I96: =I24*I60/1000 -> 5825.4 | J96: =J24*J60/1000 -> 5883.654 | K96: =K24*K60/1000 -> 5942.4905 | L96: =L24*L60/1000 -> 6001.9154 | M96: =M24*M60/1000 -> 6061.9346 | N96: =N24*N60/1000 -> 6122.5539 | O96: =O24*O60/1000 -> 6183.7795 | P96: =P24*P60/1000 -> 6245.6173 | ... W96: =W24*W60/1000 -> 6696.1471
B98: =+B86+1 -> 9 | C98: VPPA settlement cash flow to offtaker
C99: =Inputs!$C$23 -> ES-PV1 | D99: =Inputs!$D$23 -> Spain | E99: =Inputs!$E$23 -> Solar PV | F99: EUR k | G99: =SUM(I99:W99) -> 26411.446 | I99: =I75-I87 -> 2936.0016 | J99: =J75-J87 -> 2759.9534 | K99: =K75-K87 -> 2585.8829 | L99: =L75-L87 -> 2413.7573 | M99: =M75-M87 -> 2243.5444 | N99: =N75-N87 -> 2075.2122 | O99: =O75-O87 -> 1908.7294 | P99: =P75-P87 -> 1744.065 | ... W99: =W75-W87 -> 639.82136
C100: =Inputs!$C$24 -> PT-PV1 | D100: =Inputs!$D$24 -> Portugal | E100: =Inputs!$E$24 -> Solar PV | F100: EUR k | G100: =SUM(I100:W100) -> 13397.675 | I100: =I76-I88 -> 1716.96 | J100: =J76-J88 -> 1593.67 | K100: =K76-K88 -> 1471.74 | L100: =L76-L88 -> 1351.1472 | M100: =M76-M88 -> 1231.8692 | N100: =N76-N88 -> 1113.884 | O100: =O76-O88 -> 997.16986 | P100: =P76-P88 -> 881.70525 | ... W100: =W76-W88 -> 106.70359
C101: =Inputs!$C$25 -> IT-PV1 | D101: =Inputs!$D$25 -> Italy (Sud) | E101: =Inputs!$E$25 -> Solar PV | F101: EUR k | G101: =SUM(I101:W101) -> 20260.04 | I101: =I77-I89 -> 3910.464 | J101: =J77-J89 -> 3480.4833 | K101: =K77-K89 -> 3066.9558 | L101: =L77-L89 -> 2669.301 | M101: =M77-M89 -> 2286.9583 | N101: =N77-N89 -> 1919.3869 | O101: =O77-O89 -> 1566.0646 | P101: =P77-P89 -> 1226.4878 | ... W101: =W77-W89 -> -804.45087
C102: =Inputs!$C$26 -> GR-PV1 | D102: =Inputs!$D$26 -> Greece | E102: =Inputs!$E$26 -> Solar PV | F102: EUR k | G102: =SUM(I102:W102) -> 39593.926 | I102: =I78-I90 -> 4546.44 | J102: =J78-J90 -> 4243.6563 | K102: =K78-K90 -> 3948.4166 | L102: =L78-L90 -> 3660.5332 | M102: =M78-M90 -> 3379.8228 | N102: =N78-N90 -> 3106.1068 | O102: =O78-O90 -> 2839.2111 | P102: =P78-P90 -> 2578.9658 | ... W102: =W78-W90 -> 930.05804
C103: =Inputs!$C$27 -> FR-WN1 | D103: =Inputs!$D$27 -> France | E103: =Inputs!$E$27 -> Onshore wind | F103: EUR k | G103: =SUM(I103:W103) -> -2115.1321 | I103: =I79-I91 -> -131.4 | J103: =J79-J91 -> -132.714 | K103: =K79-K91 -> -134.04114 | L103: =L79-L91 -> -135.38155 | M103: =M79-M91 -> -136.73537 | N103: =N79-N91 -> -138.10272 | O103: =O79-O91 -> -139.48375 | P103: =P79-P91 -> -140.87859 | ... W103: =W79-W91 -> -151.04091
C104: =Inputs!$C$28 -> DE-WN1 | D104: =Inputs!$D$28 -> Germany | E104: =Inputs!$E$28 -> Onshore wind | F104: EUR k | G104: =SUM(I104:W104) -> 1968.6973 | I104: =I80-I92 -> 1229.904 | J104: =J80-J92 -> 1076.166 | K104: =K80-K92 -> 921.72081 | L104: =L80-L92 -> 766.55719 | M104: =M80-M92 -> 610.66385 | N104: =N80-N92 -> 454.02936 | O104: =O80-O92 -> 296.64224 | P104: =P80-P92 -> 138.49089 | ... W104: =W80-W92 -> -990.96149
C105: =Inputs!$C$29 -> NL-OW1 | D105: =Inputs!$D$29 -> Netherlands | E105: =Inputs!$E$29 -> Offshore wind | F105: EUR k | G105: =SUM(I105:W105) -> -22280.117 | I105: =I81-I93 -> 0 | J105: =J81-J93 -> -198.6768 | K105: =K81-K93 -> -400.33375 | L105: =L81-L93 -> -605.01556 | M105: =M81-M93 -> -812.76759 | N105: =N81-N93 -> -1023.6359 | O105: =O81-O93 -> -1237.6672 | P105: =P81-P93 -> -1454.9091 | ... W105: =W81-W93 -> -3069.6325
C106: =Inputs!$C$30 -> PL-WN1 | D106: =Inputs!$D$30 -> Poland | E106: =Inputs!$E$30 -> Onshore wind | F106: EUR k | G106: =SUM(I106:W106) -> 9561.8268 | I106: =I82-I94 -> 2963.07 | J106: =J82-J94 -> 2622.3169 | K106: =K82-K94 -> 2283.7121 | L106: =L82-L94 -> 1947.1937 | M106: =M82-M94 -> 1612.7004 | N106: =N82-N94 -> 1280.1716 | O106: =O82-O94 -> 949.5474 | P106: =P82-P94 -> 620.76834 | ... W106: =W82-W94 -> -1633.8913
C107: =Inputs!$C$31 -> SE-WN1 | D107: =Inputs!$D$31 -> Sweden (SE3) | E107: =Inputs!$E$31 -> Onshore wind | F107: EUR k | G107: =SUM(I107:W107) -> 20754.163 | I107: =I83-I95 -> 1561.032 | J107: =J83-J95 -> 1537.6165 | K107: =K83-K95 -> 1513.7718 | L107: =L83-L95 -> 1489.4924 | M107: =M83-M95 -> 1464.7732 | N107: =N83-N95 -> 1439.6088 | O107: =O83-O95 -> 1413.9936 | P107: =P83-P95 -> 1387.9223 | ... W107: =W83-W95 -> 1192.1739
C108: =Inputs!$C$32 -> FI-WN1 | D108: =Inputs!$D$32 -> Finland | E108: =Inputs!$E$32 -> Onshore wind | F108: EUR k | G108: =SUM(I108:W108) -> 2767.8888 | I108: =I84-I96 -> 1073.1 | J108: =J84-J96 -> 945.861 | K108: =K84-K96 -> 818.72931 | L108: =L84-L96 -> 691.69221 | M108: =M84-M96 -> 564.73698 | N108: =N84-N96 -> 437.85091 | O108: =O84-O96 -> 311.02133 | P108: =P84-P96 -> 184.23552 | ... W108: =W84-W96 -> -703.10409
B110: =+B98+1 -> 10 | C110: Net electricity cost after VPPA
...

Sheet Results
C1: Results
C2: Offer ranking and valuation (discounted at the offtaker's rate)
B4: 1 | C4: Headline
C5: Best offer by NPV | E5: =INDEX($C$13:$C$22,MATCH(MAX($M$13:$M$22),$M$13:$M$22,0))&" - "&INDEX($D$13:$D$22,MATCH(MAX($M$13:$M$22),$M$13:$M$22,0)) -> GR-PV1 - Greece
C6: NPV of best offer (EUR k) | E6: =MAX($M$13:$M$22) -> 26327.075
C7: Offers with positive NPV | E7: =COUNTIF($M$13:$M$22,">0")&" of 10" -> 8 of 10
C8: Active price scenario | E8: =Scenario -> Base
B10: =+B4+1 -> 2 | C10: Offer comparison
C12: Offer ID | D12: Country / zone | E12: Technology | F12: Capacity (MW) | G12: Lifetime gen. (GWh) | H12: Avg. coverage | I12: Avg. capture (EUR/MWh) | J12: Strike yr 1 (EUR/MWh) | K12: Avg. spread (EUR/MWh) | L12: Total settlement (EUR k) | M12: NPV (EUR k) | N12: NPV per MWh (EUR) | O12: Breakeven strike (EUR/MWh) | P12: Strike headroom (EUR/MWh) | Q12: Avg. saving | R12: Rank | S12: Verdict
C13: =Inputs!$C$23 -> ES-PV1 | D13: =Inputs!$D$23 -> Spain | E13: =Inputs!$E$23 -> Solar PV | F13: =Inputs!$F$23 -> 95 | G13: =Calc!G15/1000 -> 2531.6384 | H13: =Calc!G27 -> 0.70323288 | I13: =Calc!G39 -> 51.173411 | J13: =Inputs!$N$23 -> 38 | K13: =Calc!G63 -> 10.432551 | L13: =Calc!G99 -> 26411.446 | M13: =SUMPRODUCT(Calc!I99:W99,Calc!I$7:W$7) -> 17459.184 | N13: =IF(G13=0,0,M13/(G13*1000)*1000) -> 6.8963972 | O13: =IFERROR(J13*SUMPRODUCT(Calc!I75:W75,Calc!I$7:W$7)/SUMPRODUCT(Calc!I87:W87,Calc!I$7:W$7),0) -> 49.006493 | P13: =O13-J13 -> 11.006493 | Q13: =Calc!G123 -> 0.074893592 | R13: =RANK(M13,$M$13:$M$22,0) -> 2 | S13: =IF(M13>0,"Value accretive","Out of the money") -> Value accretive
C14: =Inputs!$C$24 -> PT-PV1 | D14: =Inputs!$D$24 -> Portugal | E14: =Inputs!$E$24 -> Solar PV | F14: =Inputs!$F$24 -> 70 | G14: =Calc!G16/1000 -> 1776.5883 | H14: =Calc!G28 -> 0.49349676 | I14: =Calc!G40 -> 50.426354 | J14: =Inputs!$N$24 -> 40 | K14: =Calc!G64 -> 7.5412378 | L14: =Calc!G100 -> 13397.675 | M14: =SUMPRODUCT(Calc!I100:W100,Calc!I$7:W$7) -> 9229.3407 | N14: =IF(G14=0,0,M14/(G14*1000)*1000) -> 5.1949799 | O14: =IFERROR(J14*SUMPRODUCT(Calc!I76:W76,Calc!I$7:W$7)/SUMPRODUCT(Calc!I88:W88,Calc!I$7:W$7),0) -> 48.29107 | P14: =O14-J14 -> 8.2910696 | Q14: =Calc!G124 -> 0.037991105 | R14: =RANK(M14,$M$13:$M$22,0) -> 6 | S14: =IF(M14>0,"Value accretive","Out of the money") -> Value accretive
C15: =Inputs!$C$25 -> IT-PV1 | D15: =Inputs!$D$25 -> Italy (Sud) | E15: =Inputs!$E$25 -> Solar PV | F15: =Inputs!$F$25 -> 80 | G15: =Calc!G17/1000 -> 1827.348 | H15: =Calc!G29 -> 0.50759667 | I15: =Calc!G41 -> 89.087127 | J15: =Inputs!$N$25 -> 78 | K15: =Calc!G65 -> 11.087127 | L15: =Calc!G101 -> 20260.04 | M15: =SUMPRODUCT(Calc!I101:W101,Calc!I$7:W$7) -> 15882.637 | N15: =IF(G15=0,0,M15/(G15*1000)*1000) -> 8.6916323 | O15: =IFERROR(J15*SUMPRODUCT(Calc!I77:W77,Calc!I$7:W$7)/SUMPRODUCT(Calc!I89:W89,Calc!I$7:W$7),0) -> 92.67741 | P15: =J15-O15 | Q15: =Calc!G125 -> 0.057450364 | R15: =RANK(M15,$M$13:$M$22,0) -> 3 | S15: =IF(M15>0,"Value accretive","Out of the money") -> Value accretive
C16: =Inputs!$C$26 -> GR-PV1 | D16: =Inputs!$D$26 -> Greece | E16: =Inputs!$E$26 -> Solar PV | F16: =Inputs!$F$26 -> 75 | G16: =Calc!G18/1000 -> 1903.4875 | H16: =Calc!G30 -> 0.52874653 | I16: =Calc!G42 -> 80.847351 | J16: =Inputs!$N$26 -> 58 | K16: =Calc!G66 -> 20.800728 | L16: =Calc!G102 -> 39593.926 | M16: =SUMPRODUCT(Calc!I102:W102,Calc!J$7:X$7) | N16: =IF(G16=0,0,M16/(G16*1000)*1000) -> 13.830968 | O16: =IFERROR(J16*SUMPRODUCT(Calc!I78:W78,Calc!I$7:W$7)/SUMPRODUCT(Calc!I90:W90,Calc!I$7:W$7),0) -> 80.70932 | P16: =O16-J16 -> 22.70932 | Q16: =Calc!G126 -> 0.11227448 | R16: =RANK(M16,$M$13:$M$22,0) -> 1 | S16: =IF(M16>0,"Value accretive","Out of the money") -> Value accretive
C17: =Inputs!$C$27 -> FR-WN1 | D17: =Inputs!$D$27 -> France | E17: =Inputs!$E$27 -> Onshore wind | F17: =Inputs!$F$27 -> 60 | G17: =Calc!G19/1000 -> 1971 | H17: =Calc!G31 -> 0.5475 | I17: =Calc!G43 -> 67.606961 | J17: =Inputs!$N$27 -> 64 | K17: =Calc!G67 -> -1.0731264 | L17: =Calc!G103 -> -2115.1321 | M17: =SUMPRODUCT(Calc!I103:W103,Calc!I$7:W$7) -> -1227.904 | N17: =IF(G17=0,0,M17/(G17*1000)*1000) -> -0.62298529 | O17: =IFERROR(J17*SUMPRODUCT(Calc!I79:W79,Calc!I$7:W$7)/SUMPRODUCT(Calc!I91:W91,Calc!I$7:W$7),0) -> 63 | P17: =O17-J17 -> -1 | Q17: =Calc!G127 -> -0.0059977723 | R17: =RANK(M17,$M$13:$M$22,0) -> 9 | S17: =IF(M17>0,"Value accretive","Out of the money") -> Out of the money
C18: =Inputs!$C$28 -> DE-WN1 | D18: =Inputs!$D$28 -> Germany | E18: =Inputs!$E$28 -> Onshore wind | F18: =Inputs!$F$28 -> 65 | G18: =Calc!G20/1000 -> 2049.84 | H18: =Calc!G32 -> 0.5694 | I18: =Calc!G44 -> 78.225514 | J18: =Inputs!$N$28 -> 72 | K18: =Calc!G68 -> 0.9604151 | L18: =Calc!G104 -> 1968.6973 | M18: =SUMPRODUCT(Calc!I104:W104,Calc!I$7:W$7) -> 3010.0848 | N18: =IF(G18=0,0,M18/(G18*1000)*1000) -> 1.4684487 | O18: =IFERROR(J18*SUMPRODUCT(Calc!I80:W80,Calc!I$7:W$7)/SUMPRODUCT(Calc!I92:W92,Calc!I$7:W$7),0) -> 74.357116 | P18: =O18-J18 -> 2.3571161 | Q18: =Calc!G128 -> 0.0055825346 | R18: =RANK(M18,$M$13:$M$22,0) -> 8 | S18: =IF(M18>0,"Value accretive","Out of the money") -> Value accretive
C19: =Inputs!$C$29 -> NL-OW1 | D19: =Inputs!$D$29 -> Netherlands | E19: =Inputs!$E$29 -> Offshore wind | F19: =Inputs!$F$29 -> 45 | G19: =Calc!G21/1000 -> 2483.46 | H19: =Calc!G33 -> 0.68985 | I19: =Calc!G45 -> 80 | J19: =Inputs!$N$29 -> 80 | K19: =Calc!G69 -> -8.9714015 | L19: =Calc!G105 -> -22280.117 | M19: =SUMPRODUCT(Calc!I105:W105,Calc!I$7:W$7) -> -10554.612 | N19: =IF(G19=0,0,M19/(G19*1000)*1000) -> -4.2499625 | O19: =IFERROR(J19*SUMPRODUCT(Calc!I81:W81,Calc!I$7:W$7)/SUMPRODUCT(Calc!I93:W93,Calc!I$7:W$7),0) -> 73.373827 | P19: =O19-J19 -> -6.6261735 | Q19: =Calc!G129 -> -0.063178592 | R19: =RANK(M19,$M$13:$M$22,0) -> 10 | S19: =IF(M19>0,"Value accretive","Out of the money") -> Out of the money
C20: =Inputs!$C$30 -> PL-WN1 | D20: =Inputs!$D$30 -> Poland | E20: =Inputs!$E$30 -> Onshore wind | F20: =Inputs!$F$30 -> 55 | G20: =Calc!G22/1000 -> 2168.1 | H20: =Calc!G34 -> 0.60225 | I20: =Calc!G46 -> 92.406596 | J20: =Inputs!$N$30 -> 82 | K20: =Calc!G70 -> 4.4102333 | L20: =Calc!G106 -> 9561.8268 | M20: =SUMPRODUCT(Calc!I106:W106,Calc!I$7:W$7) -> 9467.7394 | N20: =IF(G20=0,0,M20/(G20*1000)*1000) -> 4.366837 | O20: =IFERROR(J20*SUMPRODUCT(Calc!I82:W82,Calc!I$7:W$7)/SUMPRODUCT(Calc!I94:W94,Calc!I$7:W$7),0) -> 89.009535 | P20: =O20-J20 -> 7.0095347 | Q20: =Calc!G130 -> 0.027113985 | R20: =RANK(M20,$M$13:$M$22,0) -> 5 | S20: =IF(M20>0,"Value accretive","Out of the money") -> Value accretive
C21: =Inputs!$C$31 -> SE-WN1 | D21: =Inputs!$D$31 -> Sweden (SE3) | E21: =Inputs!$E$31 -> Onshore wind | F21: =Inputs!$F$31 -> 60 | G21: =Calc!G23/1000 -> 2601.72 | H21: =Calc!G35 -> 0.7227 | I21: =Calc!G47 -> 46.609643 | J21: =Inputs!$N$31 -> 36 | K21: =Calc!G71 -> 7.9770933 | L21: =Calc!G107 -> 20754.163 | M21: =SUMPRODUCT(Calc!I107:W107,Calc!I$7:W$7) -> 12515.411 | N21: =IF(G21=0,0,M21/(G21*1000)*1000) -> 4.8104372 | O21: =IFERROR(J21*SUMPRODUCT(Calc!I83:W83,Calc!I$7:W$7)/SUMPRODUCT(Calc!I95:W95,Calc!I$7:W$7),0) -> 43.72159 | P21: =O21-J21 -> 7.7215904 | Q21: =Calc!G131 -> 0.058851523 | R21: =RANK(M21,$M$13:$M$22,0) -> 4 | S21: =IF(M21>0,"Value accretive","Out of the money") -> Value accretive
C22: =Inputs!$C$32 -> FI-WN1 | D22: =Inputs!$D$32 -> Finland | E22: =Inputs!$E$32 -> Onshore wind | F22: =Inputs!$F$32 -> 50 | G22: =Calc!G24/1000 -> 2299.5 | H22: =Calc!G36 -> 0.63875 | I22: =Calc!G48 -> 41.982494 | J22: =Inputs!$N$32 -> 38 | K22: =Calc!G72 -> 1.2036916 | L22: =Calc!G108 -> 2767.8888 | M22: =SUMPRODUCT(Calc!I108:W108,Calc!I$7:W$7) -> 3111.337 | N22: =IF(G22=0,0,M22/(G22*1000)*1000) -> 1.3530493 | O22: =IFERROR(J22*SUMPRODUCT(Calc!I84:W84,Calc!I$7:W$7)/SUMPRODUCT(Calc!I96:W96,Calc!I$7:W$7),0) -> 40.17188 | P22: =O22-J22 -> 2.1718801 | Q22: =Calc!G132 -> 0.0078487613 | R22: =RANK(M22,$M$13:$M$22,0) -> 7 | S22: =IF(M22>0,"Value accretive","Out of the money") -> Value accretive

Sheet Project View
C1: Project View
C2: Pick an offer to see its year-by-year profile
C4: Selected offer | D4: ES-PV1
C5: Position in register | D5: =MATCH(D4,Inputs!$C$23:$C$32,0) -> 1
C6: Country / technology | D6: =INDEX(Inputs!$D$23:$D$32,$D$5)&" - "&INDEX(Inputs!$E$23:$E$32,$D$5) -> Spain - Solar PV
C7: Capacity (MW) | D7: =INDEX(Inputs!$F$23:$F$32,$D$5) -> 95
C8: NPV (EUR k) | D8: =INDEX(Results!$M$13:$M$22,$D$5) -> 17459.184
C9: Rank among offers | D9: =INDEX(Results!$R$13:$R$22,$D$5) -> 2
G10: Total / avg
C11: Annual profile
C13: Calendar year | I13: =Calc!I5 -> 2027 | J13: =Calc!J5 -> 2028 | K13: =Calc!K5 -> 2029 | L13: =Calc!L5 -> 2030 | M13: =Calc!M5 -> 2031 | N13: =Calc!N5 -> 2032 | O13: =Calc!O5 -> 2033 | P13: =Calc!P5 -> 2034 | ... W13: =Calc!W5 -> 2041
C14: Generation | D14: MWh | G14: =INDEX(Calc!G15:G24,$D$5) -> 2531638.4 | I14: =INDEX(Calc!I15:I24,$D$5) -> 174762 | J14: =INDEX(Calc!J15:J24,$D$5) -> 173888.19 | K14: =INDEX(Calc!K15:K24,$D$5) -> 173018.75 | L14: =INDEX(Calc!L15:L24,$D$5) -> 172153.66 | M14: =INDEX(Calc!M15:M24,$D$5) -> 171292.89 | N14: =INDEX(Calc!N15:N24,$D$5) -> 170436.42 | O14: =INDEX(Calc!O15:O24,$D$5) -> 169584.24 | P14: =INDEX(Calc!P15:P24,$D$5) -> 168736.32 | ... W14: =INDEX(Calc!W15:W24,$D$5) -> 162918.4
C15: Demand coverage | D15: % | G15: =INDEX(Calc!G27:G36,$D$5) -> 0.70323288 | I15: =INDEX(Calc!I27:I36,$D$5) -> 0.728175 | J15: =INDEX(Calc!J27:J36,$D$5) -> 0.72453413 | K15: =INDEX(Calc!K27:K36,$D$5) -> 0.72091145 | L15: =INDEX(Calc!L27:L36,$D$5) -> 0.7173069 | M15: =INDEX(Calc!M27:M36,$D$5) -> 0.71372036 | N15: =INDEX(Calc!N27:N36,$D$5) -> 0.71015176 | O15: =INDEX(Calc!O27:O36,$D$5) -> 0.706601 | P15: =INDEX(Calc!P27:P36,$D$5) -> 0.703068 | ... W15: =INDEX(Calc!W27:W36,$D$5) -> 0.67882667
C16: Capture price | D16: EUR/MWh | G16: =INDEX(Calc!G39:G48,$D$5) -> 51.173411 | I16: =INDEX(Calc!I39:I48,$D$5) -> 54.8 | J16: =INDEX(Calc!J39:J48,$D$5) -> 54.252 | K16: =INDEX(Calc!K39:K48,$D$5) -> 53.70948 | L16: =INDEX(Calc!L39:L48,$D$5) -> 53.172385 | M16: =INDEX(Calc!M39:M48,$D$5) -> 52.640661 | N16: =INDEX(Calc!N39:N48,$D$5) -> 52.114255 | O16: =INDEX(Calc!O39:O48,$D$5) -> 51.593112 | P16: =INDEX(Calc!P39:P48,$D$5) -> 51.077181 | ... W16: =INDEX(Calc!W39:W48,$D$5) -> 47.607271
C17: PPA strike | D17: EUR/MWh | G17: =INDEX(Calc!G51:G60,$D$5) -> 40.740861 | I17: =INDEX(Calc!I51:I60,$D$5) -> 38 | J17: =INDEX(Calc!J51:J60,$D$5) -> 38.38 | K17: =INDEX(Calc!K51:K60,$D$5) -> 38.7638 | L17: =INDEX(Calc!L51:L60,$D$5) -> 39.151438 | M17: =INDEX(Calc!M51:M60,$D$5) -> 39.542952 | N17: =INDEX(Calc!N51:N60,$D$5) -> 39.938382 | O17: =INDEX(Calc!O51:O60,$D$5) -> 40.337766 | P17: =INDEX(Calc!P51:P60,$D$5) -> 40.741143 | ... W17: =INDEX(Calc!W51:W60,$D$5) -> 43.68002
C18: Settlement spread | D18: EUR/MWh | G18: =INDEX(Calc!G63:G72,$D$5) -> 10.432551 | I18: =INDEX(Calc!I63:I72,$D$5) -> 16.8 | J18: =INDEX(Calc!J63:J72,$D$5) -> 15.872 | K18: =INDEX(Calc!K63:K72,$D$5) -> 14.94568 | L18: =INDEX(Calc!L63:L72,$D$5) -> 14.020947 | M18: =INDEX(Calc!M63:M72,$D$5) -> 13.097709 | N18: =INDEX(Calc!N63:N72,$D$5) -> 12.175873 | O18: =INDEX(Calc!O63:O72,$D$5) -> 11.255346 | P18: =INDEX(Calc!P63:P72,$D$5) -> 10.336038 | ... W18: =INDEX(Calc!W63:W72,$D$5) -> 3.9272504
C19: VPPA settlement | D19: EUR k | G19: =INDEX(Calc!G99:G108,$D$5) -> 26411.446 | I19: =INDEX(Calc!I99:I108,$D$5) -> 2936.0016 | J19: =INDEX(Calc!J99:J108,$D$5) -> 2759.9534 | K19: =INDEX(Calc!K99:K108,$D$5) -> 2585.8829 | L19: =INDEX(Calc!L99:L108,$D$5) -> 2413.7573 | M19: =INDEX(Calc!M99:M108,$D$5) -> 2243.5444 | N19: =INDEX(Calc!N99:N108,$D$5) -> 2075.2122 | O19: =INDEX(Calc!O99:O108,$D$5) -> 1908.7294 | P19: =INDEX(Calc!P99:P108,$D$5) -> 1744.065 | ... W19: =INDEX(Calc!W99:W108,$D$5) -> 639.82136
C20: Unhedged electricity cost | D20: EUR k | G20: =Calc!G12 -> 352652.95 | I20: =Calc!I12 -> 25200 | J20: =Calc!J12 -> 24948 | K20: =Calc!K12 -> 24698.52 | L20: =Calc!L12 -> 24451.535 | M20: =Calc!M12 -> 24207.019 | N20: =Calc!N12 -> 23964.949 | O20: =Calc!O12 -> 23725.3 | P20: =Calc!P12 -> 23488.047 | ... W20: =Calc!W12 -> 21892.394
C21: Net cost after VPPA | D21: EUR k | G21: =INDEX(Calc!G111:G120,$D$5) -> 326241.5 | I21: =INDEX(Calc!I111:I120,$D$5) -> 22263.998 | J21: =INDEX(Calc!J111:J120,$D$5) -> 22188.047 | K21: =INDEX(Calc!K111:K120,$D$5) -> 22112.637 | L21: =INDEX(Calc!L111:L120,$D$5) -> 22037.777 | M21: =INDEX(Calc!M111:M120,$D$5) -> 21963.475 | N21: =INDEX(Calc!N111:N120,$D$5) -> 21889.737 | O21: =INDEX(Calc!O111:O120,$D$5) -> 21816.57 | P21: =INDEX(Calc!P111:P120,$D$5) -> 21743.982 | ... W21: =INDEX(Calc!W111:W120,$D$5) -> 21252.573
C22: Saving vs unhedged | D22: % | G22: =INDEX(Calc!G123:G132,$D$5) -> 0.074893592 | I22: =INDEX(Calc!I123:I132,$D$5) -> 0.116508 | J22: =INDEX(Calc!J123:J132,$D$5) -> 0.11062824 | K22: =INDEX(Calc!K123:K132,$D$5) -> 0.10469789 | L22: =INDEX(Calc!L123:L132,$D$5) -> 0.098715984 | M22: =INDEX(Calc!M123:M132,$D$5) -> 0.092681562 | N22: =INDEX(Calc!N123:N132,$D$5) -> 0.086593641 | O22: =INDEX(Calc!O123:O132,$D$5) -> 0.080451223 | P22: =INDEX(Calc!P123:P132,$D$5) -> 0.074253299 | ... W22: =INDEX(Calc!W123:W132,$D$5) -> 0.029225737
