Workbook

Sheet Assumptions
A1: NVIDIA long-term assumptions (based on public estimates, rounded)
A2: Assumption | B2: 2027E | C2: 2028E | D2: 2029E | E2: 2030E | F2: 2031E | G2: 2032E
A3: Revenue growth | B3: 0.87 | C3: 0.7 | D3: 0.27 | E3: 0.21 | F3: 0.14 | G3: 0.08
A4: Gross margin | B4: 0.745 | C4: 0.75 | D4: 0.75 | E4: 0.75 | F4: 0.75 | G4: 0.75
A5: R&D % of revenue | B5: 0.063 | C5: 0.054 | D5: 0.05 | E5: 0.048 | F5: 0.047 | G5: 0.046
A6: Sales & marketing % of revenue | B6: 0.014 | C6: 0.012 | D6: 0.012 | E6: 0.011 | F6: 0.011 | G6: 0.011
A7: G&A % of revenue | B7: 0.007 | C7: 0.006 | D7: 0.006 | E7: 0.006 | F7: 0.006 | G7: 0.006
A8: Other opex % of revenue | B8: 0.003 | C8: 0.003 | D8: 0.002 | E8: 0.002 | F8: 0.002 | G8: 0.001
A9: D&A % of revenue | B9: 0.006 | C9: 0.005 | D9: 0.005 | E9: 0.005 | F9: 0.005 | G9: 0.005

Sheet P&L
A1: NVIDIA P&L (USD bn, fiscal years, based on public estimates)
A2: Line | B2: 2025A | C2: 2026A | D2: 2027E | E2: 2028E | F2: 2029E | G2: 2030E | H2: 2031E | I2: 2032E
A3: Revenue | B3: 130.5 | C3: 215.9 | D3: =C3*(1+Assumptions!B3) | E3: =D3*(1+Assumptions!C3) | F3: =E3*(1+Assumptions!D3) | G3: =F3*(1+Assumptions!E3) | H3: =G3*(1+Assumptions!F3) | I3: =H3*(1+Assumptions!G3)
A4: Cost of revenue | B4: 32.6 | C4: 62.5 | D4: =D3*(1-Assumptions!B4) | E4: =E3*(1-Assumptions!C4) | F4: =F3*(1-Assumptions!D4) | G4: =G3*(1-Assumptions!E4) | H4: =H3*(1-Assumptions!F4) | I4: =I3*(1-Assumptions!G4)
A5: Gross profit | B5: =B3-B4 | C5: =C3-C4 | D5: =D3-D4 | E5: =E3-E4 | F5: =F3-F4 | G5: =G3-G4 | H5: =H3-H4 | I5: =I3-I4
A6: Gross margin | B6: =B5/B3 | C6: =C5/C3 | D6: =D5/D3 | E6: =E5/E3 | F6: =F5/F3 | G6: =G5/G3 | H6: =H5/H3 | I6: =I5/I3
A7: R&D | B7: 12.9 | C7: 18.5 | D7: =D3*Assumptions!B5 | E7: =E3*Assumptions!C5 | F7: =F3*Assumptions!D5 | G7: =G3*Assumptions!E5 | H7: =H3*Assumptions!F5 | I7: =I3*Assumptions!G5
A8: Sales & marketing | B8: 2.1 | C8: 2.6 | D8: =D3*Assumptions!B6 | E8: =E3*Assumptions!C6 | F8: =F3*Assumptions!D6 | G8: =G3*Assumptions!E6 | H8: =H3*Assumptions!F6 | I8: =I3*Assumptions!G6
A9: General & administrative | B9: 1.4 | C9: 2 | D9: =D3*Assumptions!B7 | E9: =E3*Assumptions!C7 | F9: =F3*Assumptions!D7 | G9: =G3*Assumptions!E7 | H9: =H3*Assumptions!F7 | I9: =I3*Assumptions!G7
A10: Other operating expenses | B10: 0 | C10: 0 | D10: =D3*Assumptions!B8 | E10: =E3*Assumptions!C8 | F10: =F3*Assumptions!D8 | G10: =G3*Assumptions!E8 | H10: =H3*Assumptions!F8 | I10: =I3*Assumptions!G8
A11: Total operating expenses | B11: =SUM(B7:B10) | C11: =SUM(C7:C10) | D11: =SUM(D7:D10) | E11: =SUM(E7:E10) | F11: =SUM(F7:F10) | G11: 45 | H11: =SUM(H7:H10) | I11: =SUM(I7:I10)
A12: EBITDA | B12: =B15+B14 | C12: =C15+C14 | D12: =D15+D14 | E12: =E15+E14 | F12: =F15+F14 | G12: =G15+G14 | H12: =H15+H14 | I12: =I15+I14
A13: EBITDA margin | B13: =B12/B3 | C13: =C12/C3 | D13: =D12/D3 | E13: =E12/E3 | F13: =F12/F3 | G13: =G12/G3 | H13: =H12/H3 | I13: =I12/I3
A14: D&A | B14: 1.9 | C14: 2.8 | D14: =D3*Assumptions!B9 | E14: =E3*Assumptions!C9 | F14: =F3*Assumptions!D9 | G14: =G3*Assumptions!E9 | H14: =H3*Assumptions!F9 | I14: =I3*Assumptions!G9
A15: EBIT | B15: =B5-B11 | C15: =C5-C11 | D15: =D5-D11 | E15: =E5-E11 | F15: =F5-F11 | G15: =G5-G11 | H15: =H5-H11 | I15: =I5-I11
A16: EBIT margin | B16: =B15/B3 | C16: =C15/C3 | D16: =D15/D3 | E16: =E15/E3 | F16: =F15/F3 | G16: =G15/G3 | H16: =H15/H3 | I16: =I15/I3
